{
  "257452000": {
    "msg_recent": {
      "mmsi": 257452000,
      "rig_name": "ASKELADDEN",
      "latitude": 61.077518,
      "longitude": 1.988212,
      "msgtime": "2026-02-04T23:32:04.4775862+00:00",
      "source": "barentswatch"
    },
    "msg_12h": null,
    "msg_1d": null,
    "msg_2d": null
  },
  "310713000": {
    "msg_recent": {
      "mmsi": 310713000,
      "rig_name": "DEEPSEA ABERDEEN",
      "latitude": 60.838372,
      "longitude": 3.581828,
      "msgtime": "2026-02-04T23:30:26+00:00",
      "source": "barentswatch"
    },
    "msg_12h": null,
    "msg_1d": null,
    "msg_2d": null
  },
  "257459000": {
    "msg_recent": {
      "mmsi": 257459000,
      "rig_name": "ASKEPOTT",
      "latitude": 60.505597,
      "longitude": 2.015098,
      "msgtime": "2026-02-04T23:31:20.2412723+00:00",
      "source": "barentswatch"
    },
    "msg_12h": null,
    "msg_1d": null,
    "msg_2d": null
  },
  "565369000": {
    "msg_recent": {
      "mmsi": 565369000,
      "rig_name": "COSLPROSPECTOR",
      "latitude": 70.674507,
      "longitude": 18.429205,
      "msgtime": "2026-02-04T23:32:00+00:00",
      "source": "barentswatch"
    },
    "msg_12h": null,
    "msg_1d": null,
    "msg_2d": null
  },
  "257095000": {
    "msg_recent": {
      "mmsi": 257095000,
      "rig_name": "LINUS",
      "latitude": 56.423185,
      "longitude": 3.210548,
      "msgtime": "2026-02-04T23:31:13.0366618+00:00",
      "source": "barentswatch"
    },
    "msg_12h": null,
    "msg_1d": null,
    "msg_2d": null
  },
  "538004905": {
    "msg_recent": {
      "mmsi": 538004905,
      "rig_name": "TRANSOCEAN SPITSBERGEN",
      "latitude": 64.865,
      "longitude": 7.635000000000001,
      "msgtime": "2026-02-03T05:49:56+00:00",
      "source": "barentswatch"
    },
    "msg_12h": null,
    "msg_1d": null,
    "msg_2d": null
  },
  "563050900": {
    "msg_recent": {
      "mmsi": 563050900,
      "rig_name": "COSLPIONEER",
      "latitude": 59.261167,
      "longitude": 2.515,
      "msgtime": "2026-02-04T23:31:58.2692059+00:00",
      "source": "barentswatch"
    },
    "msg_12h": null,
    "msg_1d": null,
    "msg_2d": null
  },
  "538010630": {
    "msg_recent": {
      "mmsi": 538010630,
      "rig_name": "NOBLE INTEGRATOR",
      "latitude": 59.87,
      "longitude": 2.566666666666667,
      "msgtime": "2026-01-31T19:17:12+00:00",
      "source": "barentswatch"
    },
    "msg_12h": null,
    "msg_1d": null,
    "msg_2d": null
  },
  "538010632": {
    "msg_recent": {
      "mmsi": 538010632,
      "rig_name": "NOBLE INVINCIBLE",
      "latitude": 56.27463,
      "longitude": 3.399613,
      "msgtime": "2026-02-04T23:30:37.4210802+00:00",
      "source": "barentswatch"
    },
    "msg_12h": null,
    "msg_1d": null,
    "msg_2d": null
  },
  "258615000": {
    "msg_recent": {
      "mmsi": 258615000,
      "rig_name": "TRANSOCEAN ENABLER",
      "latitude": 72.524092,
      "longitude": 20.344132,
      "msgtime": "2026-02-04T23:32:03.4768371+00:00",
      "source": "barentswatch"
    },
    "msg_12h": null,
    "msg_1d": null,
    "msg_2d": null
  },
  "308928000": {
    "msg_recent": {
      "mmsi": 308928000,
      "rig_name": "SCARABEO 8",
      "latitude": 65.861788,
      "longitude": 7.396728,
      "msgtime": "2026-02-04T23:32:04.4777672+00:00",
      "source": "barentswatch"
    },
    "msg_12h": null,
    "msg_1d": null,
    "msg_2d": null
  },
  "258627000": {
    "msg_recent": {
      "mmsi": 258627000,
      "rig_name": "TRANSOCEAN ENCOURAGE",
      "latitude": 65.03166666666667,
      "longitude": 6.873333333333333,
      "msgtime": "2026-02-04T19:37:51+00:00",
      "source": "barentswatch"
    },
    "msg_12h": null,
    "msg_1d": null,
    "msg_2d": null
  },
  "566391000": {
    "msg_recent": {
      "mmsi": 566391000,
      "rig_name": "COSLINNOVATOR",
      "latitude": 61.156935,
      "longitude": 3.468658,
      "msgtime": "2026-02-04T23:31:58+00:00",
      "source": "barentswatch"
    },
    "msg_12h": null,
    "msg_1d": null,
    "msg_2d": null
  },
  "636016111": {
    "msg_recent": {
      "mmsi": 636016111,
      "rig_name": "SHELF DRILLING BARSK",
      "latitude": 58.418093,
      "longitude": 1.715688,
      "msgtime": "2026-02-04T23:31:48.0616245+00:00",
      "source": "barentswatch"
    },
    "msg_12h": null,
    "msg_1d": null,
    "msg_2d": null
  },
  "565798000": {
    "msg_recent": {
      "mmsi": 565798000,
      "rig_name": "COSLPROMOTER",
      "latitude": 61.275282,
      "longitude": 2.118343,
      "msgtime": "2026-02-04T23:31:13.0330507+00:00",
      "source": "barentswatch"
    },
    "msg_12h": null,
    "msg_1d": null,
    "msg_2d": null
  },
  "310766000": {
    "msg_recent": {
      "mmsi": 310766000,
      "rig_name": "DEEPSEA ATLANTIC",
      "latitude": 61.527473,
      "longitude": 2.316757,
      "msgtime": "2026-02-04T23:31:13+00:00",
      "source": "barentswatch"
    },
    "msg_12h": null,
    "msg_1d": null,
    "msg_2d": null
  },
  "310767000": {
    "msg_recent": {
      "mmsi": 310767000,
      "rig_name": "DEEPSEA STAVANGER",
      "latitude": 60.111053,
      "longitude": 2.591298,
      "msgtime": "2026-02-04T23:31:34.6527698+00:00",
      "source": "barentswatch"
    },
    "msg_12h": null,
    "msg_1d": null,
    "msg_2d": null
  },
  "257440000": {
    "msg_recent": {
      "mmsi": 257440000,
      "rig_name": "DEEPSEA BOLLSTA",
      "latitude": 61.299788,
      "longitude": 2.361135,
      "msgtime": "2026-02-04T23:31:56.7172998+00:00",
      "source": "barentswatch"
    },
    "msg_12h": null,
    "msg_1d": null,
    "msg_2d": null
  },
  "311000483": {
    "msg_recent": {
      "mmsi": 311000483,
      "rig_name": "DEEPSEA YANTAI",
      "latitude": 60.35549,
      "longitude": 2.475795,
      "msgtime": "2026-02-04T23:31:57.2678205+00:00",
      "source": "barentswatch"
    },
    "msg_12h": null,
    "msg_1d": null,
    "msg_2d": null
  },
  "259783000": {
    "msg_recent": {
      "mmsi": 259783000,
      "rig_name": "WEST ELARA",
      "latitude": 56.548318,
      "longitude": 3.21381,
      "msgtime": "2026-02-04T23:31:48.0613915+00:00",
      "source": "barentswatch"
    },
    "msg_12h": null,
    "msg_1d": null,
    "msg_2d": null
  },
  "310776000": {
    "msg_recent": {
      "mmsi": 310776000,
      "rig_name": "DEEPSEA NORDKAPP",
      "latitude": 58.672255,
      "longitude": 2.234297,
      "msgtime": "2026-02-04T23:32:03.0364979+00:00",
      "source": "barentswatch"
    },
    "msg_12h": null,
    "msg_1d": null,
    "msg_2d": null
  }
}