{
  "fetched_at": "2026-03-12T05:53:54.219092+00:00",
  "source": "barentswatch",
  "rigs": [
    {
      "mmsi": 310776000,
      "rig_name": "DEEPSEA NORDKAPP",
      "latitude": 58.672187,
      "longitude": 2.234587,
      "msgtime": "2026-03-12T05:53:52.8149176+00:00",
      "source": "barentswatch"
    },
    {
      "mmsi": 257452000,
      "rig_name": "ASKELADDEN",
      "latitude": 61.078527,
      "longitude": 1.988158,
      "msgtime": "2026-03-12T05:53:46.6019423+00:00",
      "source": "barentswatch"
    },
    {
      "mmsi": 310713000,
      "rig_name": "DEEPSEA ABERDEEN",
      "latitude": 60.837615,
      "longitude": 3.551007,
      "msgtime": "2026-03-12T05:53:47+00:00",
      "source": "barentswatch"
    },
    {
      "mmsi": 257459000,
      "rig_name": "ASKEPOTT",
      "latitude": 60.50557,
      "longitude": 2.015122,
      "msgtime": "2026-03-12T05:52:58.6558839+00:00",
      "source": "barentswatch"
    },
    {
      "mmsi": 565369000,
      "rig_name": "COSLPROSPECTOR",
      "latitude": 72.36693,
      "longitude": 20.120543,
      "msgtime": "2026-03-12T05:53:47.6636152+00:00",
      "source": "barentswatch"
    },
    {
      "mmsi": 257095000,
      "rig_name": "LINUS",
      "latitude": 56.423193,
      "longitude": 3.210512,
      "msgtime": "2026-03-12T05:52:09.8856976+00:00",
      "source": "barentswatch"
    },
    {
      "mmsi": 563050900,
      "rig_name": "COSLPIONEER",
      "latitude": 59.246333,
      "longitude": 2.462667,
      "msgtime": "2026-03-12T05:53:45.4671866+00:00",
      "source": "barentswatch"
    },
    {
      "mmsi": 538010632,
      "rig_name": "NOBLE INVINCIBLE",
      "latitude": 56.274627,
      "longitude": 3.399605,
      "msgtime": "2026-03-12T05:52:25.4482242+00:00",
      "source": "barentswatch"
    },
    {
      "mmsi": 258615000,
      "rig_name": "TRANSOCEAN ENABLER",
      "latitude": 72.523983,
      "longitude": 20.34401,
      "msgtime": "2026-03-12T05:53:52.7828575+00:00",
      "source": "barentswatch"
    },
    {
      "mmsi": 308928000,
      "rig_name": "SCARABEO 8",
      "latitude": 65.86177,
      "longitude": 7.396768,
      "msgtime": "2026-03-12T05:53:46.6018153+00:00",
      "source": "barentswatch"
    },
    {
      "mmsi": 636016111,
      "rig_name": "SHELF DRILLING BARSK",
      "latitude": 58.418053,
      "longitude": 1.71579,
      "msgtime": "2026-03-12T05:52:03.6823868+00:00",
      "source": "barentswatch"
    },
    {
      "mmsi": 565798000,
      "rig_name": "COSLPROMOTER",
      "latitude": 61.275257,
      "longitude": 2.1184,
      "msgtime": "2026-03-12T05:52:54.467674+00:00",
      "source": "barentswatch"
    },
    {
      "mmsi": 310766000,
      "rig_name": "DEEPSEA ATLANTIC",
      "latitude": 60.41564,
      "longitude": 5.007962,
      "msgtime": "2026-03-12T05:51:21+00:00",
      "source": "barentswatch"
    },
    {
      "mmsi": 310767000,
      "rig_name": "DEEPSEA STAVANGER",
      "latitude": 60.110987,
      "longitude": 2.592157,
      "msgtime": "2026-03-12T05:51:26.4512704+00:00",
      "source": "barentswatch"
    },
    {
      "mmsi": 257440000,
      "rig_name": "DEEPSEA BOLLSTA",
      "latitude": 58.768315,
      "longitude": 2.76037,
      "msgtime": "2026-03-12T05:53:45.5687451+00:00",
      "source": "barentswatch"
    },
    {
      "mmsi": 311000483,
      "rig_name": "DEEPSEA YANTAI",
      "latitude": 59.705333,
      "longitude": 2.308507,
      "msgtime": "2026-03-12T05:52:25.4479127+00:00",
      "source": "barentswatch"
    },
    {
      "mmsi": 259783000,
      "rig_name": "WEST ELARA",
      "latitude": 59.014648,
      "longitude": 5.707937,
      "msgtime": "2026-03-12T05:53:46+00:00",
      "source": "barentswatch"
    }
  ]
}