{
  "fetched_at": "2026-06-13T22:06:33.097369+00:00",
  "source": "barentswatch",
  "rigs": [
    {
      "mmsi": 311000483,
      "rig_name": "DEEPSEA YANTAI",
      "latitude": 61.000803,
      "longitude": 3.130098,
      "msgtime": "2026-06-13T22:06:21+00:00",
      "source": "barentswatch"
    },
    {
      "mmsi": 565369000,
      "rig_name": "COSLPROSPECTOR",
      "latitude": 64.029972,
      "longitude": 6.749478,
      "msgtime": "2026-06-13T22:06:26+00:00",
      "source": "barentswatch"
    },
    {
      "mmsi": 538010632,
      "rig_name": "NOBLE INVINCIBLE",
      "latitude": 56.274643,
      "longitude": 3.39951,
      "msgtime": "2026-06-13T22:05:24.7137816+00:00",
      "source": "barentswatch"
    },
    {
      "mmsi": 258615000,
      "rig_name": "TRANSOCEAN ENABLER",
      "latitude": 72.540695,
      "longitude": 20.356217,
      "msgtime": "2026-06-13T22:06:25.1085515+00:00",
      "source": "barentswatch"
    },
    {
      "mmsi": 310713000,
      "rig_name": "DEEPSEA ABERDEEN",
      "latitude": 59.23085,
      "longitude": 2.554392,
      "msgtime": "2026-06-13T22:06:29.6341815+00:00",
      "source": "barentswatch"
    },
    {
      "mmsi": 563050900,
      "rig_name": "COSLPIONEER",
      "latitude": 59.246333,
      "longitude": 2.462667,
      "msgtime": "2026-06-13T22:06:21.9799799+00:00",
      "source": "barentswatch"
    },
    {
      "mmsi": 258627000,
      "rig_name": "TRANSOCEAN ENCOURAGE",
      "latitude": 65.133523,
      "longitude": 6.704355,
      "msgtime": "2026-06-13T22:06:29+00:00",
      "source": "barentswatch"
    },
    {
      "mmsi": 257095000,
      "rig_name": "LINUS",
      "latitude": 56.548315,
      "longitude": 3.213837,
      "msgtime": "2026-06-13T22:06:17.4161683+00:00",
      "source": "barentswatch"
    },
    {
      "mmsi": 310766000,
      "rig_name": "DEEPSEA ATLANTIC",
      "latitude": 60.41564,
      "longitude": 5.007887,
      "msgtime": "2026-06-13T22:05:01+00:00",
      "source": "barentswatch"
    },
    {
      "mmsi": 310767000,
      "rig_name": "DEEPSEA STAVANGER",
      "latitude": 60.221567,
      "longitude": 2.496768,
      "msgtime": "2026-06-13T22:06:27+00:00",
      "source": "barentswatch"
    },
    {
      "mmsi": 566391000,
      "rig_name": "COSLINNOVATOR",
      "latitude": 59.340885,
      "longitude": 2.22278,
      "msgtime": "2026-06-13T22:05:14.2906479+00:00",
      "source": "barentswatch"
    },
    {
      "mmsi": 310776000,
      "rig_name": "DEEPSEA NORDKAPP",
      "latitude": 58.969512,
      "longitude": 2.281225,
      "msgtime": "2026-06-13T22:06:29.6341615+00:00",
      "source": "barentswatch"
    },
    {
      "mmsi": 259783000,
      "rig_name": "WEST ELARA",
      "latitude": 59.617925,
      "longitude": 2.494657,
      "msgtime": "2026-06-13T22:04:09.8236908+00:00",
      "source": "barentswatch"
    },
    {
      "mmsi": 636016111,
      "rig_name": "SHELF DRILLING BARSK",
      "latitude": 58.418053,
      "longitude": 1.715817,
      "msgtime": "2026-06-13T22:03:29.5069049+00:00",
      "source": "barentswatch"
    },
    {
      "mmsi": 257440000,
      "rig_name": "DEEPSEA BOLLSTA",
      "latitude": 58.80606,
      "longitude": 2.709628,
      "msgtime": "2026-06-13T22:06:21.9809801+00:00",
      "source": "barentswatch"
    },
    {
      "mmsi": 257452000,
      "rig_name": "ASKELADDEN",
      "latitude": 61.096798,
      "longitude": 2.275033,
      "msgtime": "2026-06-13T22:06:28+00:00",
      "source": "barentswatch"
    },
    {
      "mmsi": 257459000,
      "rig_name": "ASKEPOTT",
      "latitude": 60.505998,
      "longitude": 2.040975,
      "msgtime": "2026-06-13T22:06:00+00:00",
      "source": "barentswatch"
    },
    {
      "mmsi": 308928000,
      "rig_name": "SCARABEO 8",
      "latitude": 66.001108,
      "longitude": 7.79896,
      "msgtime": "2026-06-13T22:06:29.6341711+00:00",
      "source": "barentswatch"
    },
    {
      "mmsi": 565798000,
      "rig_name": "COSLPROMOTER",
      "latitude": 58.496113,
      "longitude": 1.721283,
      "msgtime": "2026-06-13T22:05:12.2856739+00:00",
      "source": "barentswatch"
    }
  ]
}