{
  "fetched_at": "2026-01-14T19:36:32.047337+00:00",
  "source": "barentswatch",
  "rigs": [
    {
      "mmsi": 310776000,
      "rig_name": "DEEPSEA NORDKAPP",
      "latitude": 58.672293,
      "longitude": 2.234357,
      "msgtime": "2026-01-14T19:36:22.9985289+00:00",
      "source": "barentswatch"
    },
    {
      "mmsi": 257452000,
      "rig_name": "ASKELADDEN",
      "latitude": 61.077518,
      "longitude": 1.988203,
      "msgtime": "2026-01-14T19:36:24.998273+00:00",
      "source": "barentswatch"
    },
    {
      "mmsi": 310713000,
      "rig_name": "DEEPSEA ABERDEEN",
      "latitude": 60.838342,
      "longitude": 3.582043,
      "msgtime": "2026-01-14T19:33:29+00:00",
      "source": "barentswatch"
    },
    {
      "mmsi": 257459000,
      "rig_name": "ASKEPOTT",
      "latitude": 60.505592,
      "longitude": 2.015137,
      "msgtime": "2026-01-14T19:35:01.538257+00:00",
      "source": "barentswatch"
    },
    {
      "mmsi": 565369000,
      "rig_name": "COSLPROSPECTOR",
      "latitude": 70.674437,
      "longitude": 18.429077,
      "msgtime": "2026-01-14T19:36:21+00:00",
      "source": "barentswatch"
    },
    {
      "mmsi": 257095000,
      "rig_name": "LINUS",
      "latitude": 56.423155,
      "longitude": 3.210518,
      "msgtime": "2026-01-14T19:36:29.1989099+00:00",
      "source": "barentswatch"
    },
    {
      "mmsi": 563050900,
      "rig_name": "COSLPIONEER",
      "latitude": 59.217667,
      "longitude": 2.424667,
      "msgtime": "2026-01-14T19:35:19.2264574+00:00",
      "source": "barentswatch"
    },
    {
      "mmsi": 538010632,
      "rig_name": "NOBLE INVINCIBLE",
      "latitude": 56.274605,
      "longitude": 3.39959,
      "msgtime": "2026-01-14T19:34:24.517089+00:00",
      "source": "barentswatch"
    },
    {
      "mmsi": 258615000,
      "rig_name": "TRANSOCEAN ENABLER",
      "latitude": 72.454043,
      "longitude": 20.148135,
      "msgtime": "2026-01-14T19:36:28.1964845+00:00",
      "source": "barentswatch"
    },
    {
      "mmsi": 308928000,
      "rig_name": "SCARABEO 8",
      "latitude": 65.861815,
      "longitude": 7.39688,
      "msgtime": "2026-01-14T19:36:21.9986494+00:00",
      "source": "barentswatch"
    },
    {
      "mmsi": 258627000,
      "rig_name": "TRANSOCEAN ENCOURAGE",
      "latitude": 65.031347,
      "longitude": 6.873693,
      "msgtime": "2026-01-14T19:36:24.9981315+00:00",
      "source": "barentswatch"
    },
    {
      "mmsi": 566391000,
      "rig_name": "COSLINNOVATOR",
      "latitude": 65.411707,
      "longitude": 7.396878,
      "msgtime": "2026-01-14T19:36:30.1981626+00:00",
      "source": "barentswatch"
    },
    {
      "mmsi": 636016111,
      "rig_name": "SHELF DRILLING BARSK",
      "latitude": 58.418067,
      "longitude": 1.715853,
      "msgtime": "2026-01-14T19:34:38.130442+00:00",
      "source": "barentswatch"
    },
    {
      "mmsi": 565798000,
      "rig_name": "COSLPROMOTER",
      "latitude": 58.87923,
      "longitude": 2.4866,
      "msgtime": "2026-01-14T19:36:26.1962145+00:00",
      "source": "barentswatch"
    },
    {
      "mmsi": 310766000,
      "rig_name": "DEEPSEA ATLANTIC",
      "latitude": 58.33052,
      "longitude": 1.590927,
      "msgtime": "2026-01-14T19:34:07.0969725+00:00",
      "source": "barentswatch"
    },
    {
      "mmsi": 310767000,
      "rig_name": "DEEPSEA STAVANGER",
      "latitude": 60.11098,
      "longitude": 2.59194,
      "msgtime": "2026-01-14T19:33:41+00:00",
      "source": "barentswatch"
    },
    {
      "mmsi": 257440000,
      "rig_name": "DEEPSEA BOLLSTA",
      "latitude": 61.29985,
      "longitude": 2.361002,
      "msgtime": "2026-01-14T19:36:26.1961288+00:00",
      "source": "barentswatch"
    },
    {
      "mmsi": 311000483,
      "rig_name": "DEEPSEA YANTAI",
      "latitude": 64.341803,
      "longitude": 7.721422,
      "msgtime": "2026-01-14T19:36:23+00:00",
      "source": "barentswatch"
    },
    {
      "mmsi": 259783000,
      "rig_name": "WEST ELARA",
      "latitude": 56.548305,
      "longitude": 3.213828,
      "msgtime": "2026-01-14T19:36:28.1965551+00:00",
      "source": "barentswatch"
    }
  ]
}