{
  "fetched_at": "2026-02-15T08:38:10.658105+00:00",
  "source": "barentswatch",
  "rigs": [
    {
      "mmsi": 310776000,
      "rig_name": "DEEPSEA NORDKAPP",
      "latitude": 58.67219,
      "longitude": 2.234555,
      "msgtime": "2026-02-15T08:38:05.1629569+00:00",
      "source": "barentswatch"
    },
    {
      "mmsi": 257452000,
      "rig_name": "ASKELADDEN",
      "latitude": 61.078508,
      "longitude": 1.988163,
      "msgtime": "2026-02-15T08:38:02+00:00",
      "source": "barentswatch"
    },
    {
      "mmsi": 310713000,
      "rig_name": "DEEPSEA ABERDEEN",
      "latitude": 60.838355,
      "longitude": 3.582038,
      "msgtime": "2026-02-15T08:36:11+00:00",
      "source": "barentswatch"
    },
    {
      "mmsi": 257459000,
      "rig_name": "ASKEPOTT",
      "latitude": 60.505602,
      "longitude": 2.015108,
      "msgtime": "2026-02-15T08:35:24.2818232+00:00",
      "source": "barentswatch"
    },
    {
      "mmsi": 565369000,
      "rig_name": "COSLPROSPECTOR",
      "latitude": 71.3816,
      "longitude": 19.133463,
      "msgtime": "2026-02-15T08:38:09.3620136+00:00",
      "source": "barentswatch"
    },
    {
      "mmsi": 257095000,
      "rig_name": "LINUS",
      "latitude": 56.42316,
      "longitude": 3.210488,
      "msgtime": "2026-02-15T08:36:28.486007+00:00",
      "source": "barentswatch"
    },
    {
      "mmsi": 563050900,
      "rig_name": "COSLPIONEER",
      "latitude": 59.1995,
      "longitude": 2.4075,
      "msgtime": "2026-02-15T08:36:44.2905409+00:00",
      "source": "barentswatch"
    },
    {
      "mmsi": 538010632,
      "rig_name": "NOBLE INVINCIBLE",
      "latitude": 56.27462,
      "longitude": 3.399623,
      "msgtime": "2026-02-15T08:37:43.3560604+00:00",
      "source": "barentswatch"
    },
    {
      "mmsi": 258615000,
      "rig_name": "TRANSOCEAN ENABLER",
      "latitude": 72.523653,
      "longitude": 20.34337,
      "msgtime": "2026-02-15T08:38:09.3629688+00:00",
      "source": "barentswatch"
    },
    {
      "mmsi": 308928000,
      "rig_name": "SCARABEO 8",
      "latitude": 65.861787,
      "longitude": 7.396702,
      "msgtime": "2026-02-15T08:38:03.1637192+00:00",
      "source": "barentswatch"
    },
    {
      "mmsi": 566391000,
      "rig_name": "COSLINNOVATOR",
      "latitude": 61.156907,
      "longitude": 3.468678,
      "msgtime": "2026-02-15T08:38:07+00:00",
      "source": "barentswatch"
    },
    {
      "mmsi": 636016111,
      "rig_name": "SHELF DRILLING BARSK",
      "latitude": 58.418113,
      "longitude": 1.715692,
      "msgtime": "2026-02-15T08:35:53.2860602+00:00",
      "source": "barentswatch"
    },
    {
      "mmsi": 565798000,
      "rig_name": "COSLPROMOTER",
      "latitude": 61.275353,
      "longitude": 2.118302,
      "msgtime": "2026-02-15T08:36:26.4866512+00:00",
      "source": "barentswatch"
    },
    {
      "mmsi": 310766000,
      "rig_name": "DEEPSEA ATLANTIC",
      "latitude": 61.527467,
      "longitude": 2.316705,
      "msgtime": "2026-02-15T08:34:14.2386702+00:00",
      "source": "barentswatch"
    },
    {
      "mmsi": 310767000,
      "rig_name": "DEEPSEA STAVANGER",
      "latitude": 60.110507,
      "longitude": 2.591347,
      "msgtime": "2026-02-15T08:37:37+00:00",
      "source": "barentswatch"
    },
    {
      "mmsi": 257440000,
      "rig_name": "DEEPSEA BOLLSTA",
      "latitude": 61.29977,
      "longitude": 2.361267,
      "msgtime": "2026-02-15T08:38:06.1621485+00:00",
      "source": "barentswatch"
    },
    {
      "mmsi": 311000483,
      "rig_name": "DEEPSEA YANTAI",
      "latitude": 59.705352,
      "longitude": 2.308585,
      "msgtime": "2026-02-15T08:36:54.5215572+00:00",
      "source": "barentswatch"
    },
    {
      "mmsi": 259783000,
      "rig_name": "WEST ELARA",
      "latitude": 56.548322,
      "longitude": 3.213805,
      "msgtime": "2026-02-15T08:38:07.161914+00:00",
      "source": "barentswatch"
    }
  ]
}