{
  "257452000": {
    "msg_recent": {
      "mmsi": 257452000,
      "rig_name": "ASKELADDEN",
      "latitude": 61.078497,
      "longitude": 1.988208,
      "msgtime": "2026-02-26T15:56:24.0131291+00:00",
      "source": "barentswatch"
    },
    "running_msgs": [
      {
        "msg": {
          "mmsi": 257452000,
          "rig_name": "ASKELADDEN",
          "latitude": 61.078497,
          "longitude": 1.988208,
          "msgtime": "2026-02-26T15:56:24.0131291+00:00",
          "source": "barentswatch"
        }
      }
    ],
    "msg_12h": null,
    "msg_1d": null,
    "msg_2d": null
  },
  "310713000": {
    "msg_recent": {
      "mmsi": 310713000,
      "rig_name": "DEEPSEA ABERDEEN",
      "latitude": 60.8376,
      "longitude": 3.550663,
      "msgtime": "2026-02-26T15:56:18+00:00",
      "source": "barentswatch"
    },
    "running_msgs": [
      {
        "msg": {
          "mmsi": 310713000,
          "rig_name": "DEEPSEA ABERDEEN",
          "latitude": 60.8376,
          "longitude": 3.550663,
          "msgtime": "2026-02-26T15:56:18+00:00",
          "source": "barentswatch"
        }
      }
    ],
    "msg_12h": null,
    "msg_1d": null,
    "msg_2d": null
  },
  "257459000": {
    "msg_recent": {
      "mmsi": 257459000,
      "rig_name": "ASKEPOTT",
      "latitude": 60.505595,
      "longitude": 2.015123,
      "msgtime": "2026-02-26T15:54:33.1392924+00:00",
      "source": "barentswatch"
    },
    "running_msgs": [
      {
        "msg": {
          "mmsi": 257459000,
          "rig_name": "ASKEPOTT",
          "latitude": 60.505595,
          "longitude": 2.015123,
          "msgtime": "2026-02-26T15:54:33.1392924+00:00",
          "source": "barentswatch"
        }
      }
    ],
    "msg_12h": null,
    "msg_1d": null,
    "msg_2d": null
  },
  "565369000": {
    "msg_recent": {
      "mmsi": 565369000,
      "rig_name": "COSLPROSPECTOR",
      "latitude": 72.366678,
      "longitude": 20.121408,
      "msgtime": "2026-02-26T15:56:25+00:00",
      "source": "barentswatch"
    },
    "running_msgs": [
      {
        "msg": {
          "mmsi": 565369000,
          "rig_name": "COSLPROSPECTOR",
          "latitude": 72.366678,
          "longitude": 20.121408,
          "msgtime": "2026-02-26T15:56:25+00:00",
          "source": "barentswatch"
        }
      }
    ],
    "msg_12h": null,
    "msg_1d": null,
    "msg_2d": null
  },
  "257095000": {
    "msg_recent": {
      "mmsi": 257095000,
      "rig_name": "LINUS",
      "latitude": 56.423175,
      "longitude": 3.21051,
      "msgtime": "2026-02-26T15:53:47.5177806+00:00",
      "source": "barentswatch"
    },
    "running_msgs": [
      {
        "msg": {
          "mmsi": 257095000,
          "rig_name": "LINUS",
          "latitude": 56.423175,
          "longitude": 3.21051,
          "msgtime": "2026-02-26T15:53:47.5177806+00:00",
          "source": "barentswatch"
        }
      }
    ],
    "msg_12h": null,
    "msg_1d": null,
    "msg_2d": null
  },
  "538004905": {
    "msg_recent": {
      "mmsi": 538004905,
      "rig_name": "TRANSOCEAN SPITSBERGEN",
      "latitude": 64.865,
      "longitude": 7.635000000000001,
      "msgtime": "2026-02-26T13:09:00+00:00",
      "source": "barentswatch"
    },
    "running_msgs": [
      {
        "msg": {
          "mmsi": 538004905,
          "rig_name": "TRANSOCEAN SPITSBERGEN",
          "latitude": 64.865,
          "longitude": 7.635000000000001,
          "msgtime": "2026-02-26T13:09:00+00:00",
          "source": "barentswatch"
        }
      }
    ],
    "msg_12h": null,
    "msg_1d": null,
    "msg_2d": null
  },
  "563050900": {
    "msg_recent": {
      "mmsi": 563050900,
      "rig_name": "COSLPIONEER",
      "latitude": 59.1995,
      "longitude": 2.407833,
      "msgtime": "2026-02-26T15:53:49.5182015+00:00",
      "source": "barentswatch"
    },
    "running_msgs": [
      {
        "msg": {
          "mmsi": 563050900,
          "rig_name": "COSLPIONEER",
          "latitude": 59.1995,
          "longitude": 2.407833,
          "msgtime": "2026-02-26T15:53:49.5182015+00:00",
          "source": "barentswatch"
        }
      }
    ],
    "msg_12h": null,
    "msg_1d": null,
    "msg_2d": null
  },
  "538010630": {
    "msg_recent": {
      "mmsi": 538010630,
      "rig_name": "NOBLE INTEGRATOR",
      "latitude": 59.87,
      "longitude": 2.566666666666667,
      "msgtime": "2026-02-26T14:42:16+00:00",
      "source": "barentswatch"
    },
    "running_msgs": [
      {
        "msg": {
          "mmsi": 538010630,
          "rig_name": "NOBLE INTEGRATOR",
          "latitude": 59.87,
          "longitude": 2.566666666666667,
          "msgtime": "2026-02-26T14:42:16+00:00",
          "source": "barentswatch"
        }
      }
    ],
    "msg_12h": null,
    "msg_1d": null,
    "msg_2d": null
  },
  "538010632": {
    "msg_recent": {
      "mmsi": 538010632,
      "rig_name": "NOBLE INVINCIBLE",
      "latitude": 56.274567,
      "longitude": 3.399728,
      "msgtime": "2026-02-26T15:53:58.7190996+00:00",
      "source": "barentswatch"
    },
    "running_msgs": [
      {
        "msg": {
          "mmsi": 538010632,
          "rig_name": "NOBLE INVINCIBLE",
          "latitude": 56.274567,
          "longitude": 3.399728,
          "msgtime": "2026-02-26T15:53:58.7190996+00:00",
          "source": "barentswatch"
        }
      }
    ],
    "msg_12h": null,
    "msg_1d": null,
    "msg_2d": null
  },
  "258615000": {
    "msg_recent": {
      "mmsi": 258615000,
      "rig_name": "TRANSOCEAN ENABLER",
      "latitude": 72.523768,
      "longitude": 20.344383,
      "msgtime": "2026-02-26T15:56:24+00:00",
      "source": "barentswatch"
    },
    "running_msgs": [
      {
        "msg": {
          "mmsi": 258615000,
          "rig_name": "TRANSOCEAN ENABLER",
          "latitude": 72.523768,
          "longitude": 20.344383,
          "msgtime": "2026-02-26T15:56:24+00:00",
          "source": "barentswatch"
        }
      }
    ],
    "msg_12h": null,
    "msg_1d": null,
    "msg_2d": null
  },
  "308928000": {
    "msg_recent": {
      "mmsi": 308928000,
      "rig_name": "SCARABEO 8",
      "latitude": 65.8618,
      "longitude": 7.39673,
      "msgtime": "2026-02-26T15:56:26.0184877+00:00",
      "source": "barentswatch"
    },
    "running_msgs": [
      {
        "msg": {
          "mmsi": 308928000,
          "rig_name": "SCARABEO 8",
          "latitude": 65.8618,
          "longitude": 7.39673,
          "msgtime": "2026-02-26T15:56:26.0184877+00:00",
          "source": "barentswatch"
        }
      }
    ],
    "msg_12h": null,
    "msg_1d": null,
    "msg_2d": null
  },
  "258627000": {
    "msg_recent": {
      "mmsi": 258627000,
      "rig_name": "TRANSOCEAN ENCOURAGE",
      "latitude": 65.03166666666667,
      "longitude": 6.873333333333333,
      "msgtime": "2026-02-26T14:43:53+00:00",
      "source": "barentswatch"
    },
    "running_msgs": [
      {
        "msg": {
          "mmsi": 258627000,
          "rig_name": "TRANSOCEAN ENCOURAGE",
          "latitude": 65.03166666666667,
          "longitude": 6.873333333333333,
          "msgtime": "2026-02-26T14:43:53+00:00",
          "source": "barentswatch"
        }
      }
    ],
    "msg_12h": null,
    "msg_1d": null,
    "msg_2d": null
  },
  "566391000": {
    "msg_recent": {
      "mmsi": 566391000,
      "rig_name": "COSLINNOVATOR",
      "latitude": 61.156943,
      "longitude": 3.468625,
      "msgtime": "2026-02-26T15:56:18+00:00",
      "source": "barentswatch"
    },
    "running_msgs": [
      {
        "msg": {
          "mmsi": 566391000,
          "rig_name": "COSLINNOVATOR",
          "latitude": 61.156943,
          "longitude": 3.468625,
          "msgtime": "2026-02-26T15:56:18+00:00",
          "source": "barentswatch"
        }
      }
    ],
    "msg_12h": null,
    "msg_1d": null,
    "msg_2d": null
  },
  "636016111": {
    "msg_recent": {
      "mmsi": 636016111,
      "rig_name": "SHELF DRILLING BARSK",
      "latitude": 58.418067,
      "longitude": 1.715858,
      "msgtime": "2026-02-26T15:54:08.1231821+00:00",
      "source": "barentswatch"
    },
    "running_msgs": [
      {
        "msg": {
          "mmsi": 636016111,
          "rig_name": "SHELF DRILLING BARSK",
          "latitude": 58.418067,
          "longitude": 1.715858,
          "msgtime": "2026-02-26T15:54:08.1231821+00:00",
          "source": "barentswatch"
        }
      }
    ],
    "msg_12h": null,
    "msg_1d": null,
    "msg_2d": null
  },
  "565798000": {
    "msg_recent": {
      "mmsi": 565798000,
      "rig_name": "COSLPROMOTER",
      "latitude": 61.275295,
      "longitude": 2.118397,
      "msgtime": "2026-02-26T15:55:25.1735591+00:00",
      "source": "barentswatch"
    },
    "running_msgs": [
      {
        "msg": {
          "mmsi": 565798000,
          "rig_name": "COSLPROMOTER",
          "latitude": 61.275295,
          "longitude": 2.118397,
          "msgtime": "2026-02-26T15:55:25.1735591+00:00",
          "source": "barentswatch"
        }
      }
    ],
    "msg_12h": null,
    "msg_1d": null,
    "msg_2d": null
  },
  "310766000": {
    "msg_recent": {
      "mmsi": 310766000,
      "rig_name": "DEEPSEA ATLANTIC",
      "latitude": 61.527493,
      "longitude": 2.316727,
      "msgtime": "2026-02-26T15:52:23.6529643+00:00",
      "source": "barentswatch"
    },
    "running_msgs": [
      {
        "msg": {
          "mmsi": 310766000,
          "rig_name": "DEEPSEA ATLANTIC",
          "latitude": 61.527493,
          "longitude": 2.316727,
          "msgtime": "2026-02-26T15:52:23.6529643+00:00",
          "source": "barentswatch"
        }
      }
    ],
    "msg_12h": null,
    "msg_1d": null,
    "msg_2d": null
  },
  "310767000": {
    "msg_recent": {
      "mmsi": 310767000,
      "rig_name": "DEEPSEA STAVANGER",
      "latitude": 60.110993,
      "longitude": 2.592228,
      "msgtime": "2026-02-26T15:54:28+00:00",
      "source": "barentswatch"
    },
    "running_msgs": [
      {
        "msg": {
          "mmsi": 310767000,
          "rig_name": "DEEPSEA STAVANGER",
          "latitude": 60.110993,
          "longitude": 2.592228,
          "msgtime": "2026-02-26T15:54:28+00:00",
          "source": "barentswatch"
        }
      }
    ],
    "msg_12h": null,
    "msg_1d": null,
    "msg_2d": null
  },
  "257440000": {
    "msg_recent": {
      "mmsi": 257440000,
      "rig_name": "DEEPSEA BOLLSTA",
      "latitude": 58.880212,
      "longitude": 2.487582,
      "msgtime": "2026-02-26T15:56:25.0200425+00:00",
      "source": "barentswatch"
    },
    "running_msgs": [
      {
        "msg": {
          "mmsi": 257440000,
          "rig_name": "DEEPSEA BOLLSTA",
          "latitude": 58.880212,
          "longitude": 2.487582,
          "msgtime": "2026-02-26T15:56:25.0200425+00:00",
          "source": "barentswatch"
        }
      }
    ],
    "msg_12h": null,
    "msg_1d": null,
    "msg_2d": null
  },
  "311000483": {
    "msg_recent": {
      "mmsi": 311000483,
      "rig_name": "DEEPSEA YANTAI",
      "latitude": 59.705337,
      "longitude": 2.308585,
      "msgtime": "2026-02-26T15:56:24.0127611+00:00",
      "source": "barentswatch"
    },
    "running_msgs": [
      {
        "msg": {
          "mmsi": 311000483,
          "rig_name": "DEEPSEA YANTAI",
          "latitude": 59.705337,
          "longitude": 2.308585,
          "msgtime": "2026-02-26T15:56:24.0127611+00:00",
          "source": "barentswatch"
        }
      }
    ],
    "msg_12h": null,
    "msg_1d": null,
    "msg_2d": null
  },
  "259783000": {
    "msg_recent": {
      "mmsi": 259783000,
      "rig_name": "WEST ELARA",
      "latitude": 56.548295,
      "longitude": 3.21382,
      "msgtime": "2026-02-26T15:56:08.6065248+00:00",
      "source": "barentswatch"
    },
    "running_msgs": [
      {
        "msg": {
          "mmsi": 259783000,
          "rig_name": "WEST ELARA",
          "latitude": 56.548295,
          "longitude": 3.21382,
          "msgtime": "2026-02-26T15:56:08.6065248+00:00",
          "source": "barentswatch"
        }
      }
    ],
    "msg_12h": null,
    "msg_1d": null,
    "msg_2d": null
  },
  "310776000": {
    "msg_recent": {
      "mmsi": 310776000,
      "rig_name": "DEEPSEA NORDKAPP",
      "latitude": 58.672213,
      "longitude": 2.234572,
      "msgtime": "2026-02-26T15:56:25.0192065+00:00",
      "source": "barentswatch"
    },
    "running_msgs": [
      {
        "msg": {
          "mmsi": 310776000,
          "rig_name": "DEEPSEA NORDKAPP",
          "latitude": 58.672213,
          "longitude": 2.234572,
          "msgtime": "2026-02-26T15:56:25.0192065+00:00",
          "source": "barentswatch"
        }
      }
    ],
    "msg_12h": null,
    "msg_1d": null,
    "msg_2d": null
  },
  "310776000": {
    "msg_recent": {
      "mmsi": 310776000,
      "rig_name": "DEEPSEA NORDKAPP",
      "latitude": 58.67221,
      "longitude": 2.234545,
      "msgtime": "2026-02-26T17:05:53.3661845+00:00",
      "source": "barentswatch"
    },
    "running_msgs": [
      {
        "msg": {
          "mmsi": 310776000,
          "rig_name": "DEEPSEA NORDKAPP",
          "latitude": 58.67221,
          "longitude": 2.234545,
          "msgtime": "2026-02-26T17:05:53.3661845+00:00",
          "source": "barentswatch"
        }
      }
    ],
    "msg_12h": null,
    "msg_1d": null,
    "msg_2d": null
  },
  "257452000": {
    "msg_recent": {
      "mmsi": 257452000,
      "rig_name": "ASKELADDEN",
      "latitude": 61.078507,
      "longitude": 1.988227,
      "msgtime": "2026-02-26T17:05:54.3665008+00:00",
      "source": "barentswatch"
    },
    "running_msgs": [
      {
        "msg": {
          "mmsi": 257452000,
          "rig_name": "ASKELADDEN",
          "latitude": 61.078507,
          "longitude": 1.988227,
          "msgtime": "2026-02-26T17:05:54.3665008+00:00",
          "source": "barentswatch"
        }
      }
    ],
    "msg_12h": null,
    "msg_1d": null,
    "msg_2d": null
  },
  "310713000": {
    "msg_recent": {
      "mmsi": 310713000,
      "rig_name": "DEEPSEA ABERDEEN",
      "latitude": 60.837578,
      "longitude": 3.550657,
      "msgtime": "2026-02-26T17:05:57+00:00",
      "source": "barentswatch"
    },
    "running_msgs": [
      {
        "msg": {
          "mmsi": 310713000,
          "rig_name": "DEEPSEA ABERDEEN",
          "latitude": 60.837578,
          "longitude": 3.550657,
          "msgtime": "2026-02-26T17:05:57+00:00",
          "source": "barentswatch"
        }
      }
    ],
    "msg_12h": null,
    "msg_1d": null,
    "msg_2d": null
  },
  "257459000": {
    "msg_recent": {
      "mmsi": 257459000,
      "rig_name": "ASKEPOTT",
      "latitude": 60.505608,
      "longitude": 2.015162,
      "msgtime": "2026-02-26T17:03:33.8655993+00:00",
      "source": "barentswatch"
    },
    "running_msgs": [
      {
        "msg": {
          "mmsi": 257459000,
          "rig_name": "ASKEPOTT",
          "latitude": 60.505608,
          "longitude": 2.015162,
          "msgtime": "2026-02-26T17:03:33.8655993+00:00",
          "source": "barentswatch"
        }
      }
    ],
    "msg_12h": null,
    "msg_1d": null,
    "msg_2d": null
  },
  "565369000": {
    "msg_recent": {
      "mmsi": 565369000,
      "rig_name": "COSLPROSPECTOR",
      "latitude": 72.366638,
      "longitude": 20.121385,
      "msgtime": "2026-02-26T17:05:57+00:00",
      "source": "barentswatch"
    },
    "running_msgs": [
      {
        "msg": {
          "mmsi": 565369000,
          "rig_name": "COSLPROSPECTOR",
          "latitude": 72.366638,
          "longitude": 20.121385,
          "msgtime": "2026-02-26T17:05:57+00:00",
          "source": "barentswatch"
        }
      }
    ],
    "msg_12h": null,
    "msg_1d": null,
    "msg_2d": null
  },
  "257095000": {
    "msg_recent": {
      "mmsi": 257095000,
      "rig_name": "LINUS",
      "latitude": 56.423172,
      "longitude": 3.21053,
      "msgtime": "2026-02-26T17:05:50.1611737+00:00",
      "source": "barentswatch"
    },
    "running_msgs": [
      {
        "msg": {
          "mmsi": 257095000,
          "rig_name": "LINUS",
          "latitude": 56.423172,
          "longitude": 3.21053,
          "msgtime": "2026-02-26T17:05:50.1611737+00:00",
          "source": "barentswatch"
        }
      }
    ],
    "msg_12h": null,
    "msg_1d": null,
    "msg_2d": null
  },
  "538004905": {
    "msg_recent": {
      "mmsi": 538004905,
      "rig_name": "TRANSOCEAN SPITSBERGEN",
      "latitude": 64.865,
      "longitude": 7.635000000000001,
      "msgtime": "2026-02-26T16:59:59+00:00",
      "source": "barentswatch"
    },
    "running_msgs": [
      {
        "msg": {
          "mmsi": 538004905,
          "rig_name": "TRANSOCEAN SPITSBERGEN",
          "latitude": 64.865,
          "longitude": 7.635000000000001,
          "msgtime": "2026-02-26T16:59:59+00:00",
          "source": "barentswatch"
        }
      }
    ],
    "msg_12h": null,
    "msg_1d": null,
    "msg_2d": null
  },
  "563050900": {
    "msg_recent": {
      "mmsi": 563050900,
      "rig_name": "COSLPIONEER",
      "latitude": 59.1985,
      "longitude": 2.409,
      "msgtime": "2026-02-26T17:05:51.1646232+00:00",
      "source": "barentswatch"
    },
    "running_msgs": [
      {
        "msg": {
          "mmsi": 563050900,
          "rig_name": "COSLPIONEER",
          "latitude": 59.1985,
          "longitude": 2.409,
          "msgtime": "2026-02-26T17:05:51.1646232+00:00",
          "source": "barentswatch"
        }
      }
    ],
    "msg_12h": null,
    "msg_1d": null,
    "msg_2d": null
  },
  "538010632": {
    "msg_recent": {
      "mmsi": 538010632,
      "rig_name": "NOBLE INVINCIBLE",
      "latitude": 56.27456,
      "longitude": 3.399672,
      "msgtime": "2026-02-26T17:05:54.3666932+00:00",
      "source": "barentswatch"
    },
    "running_msgs": [
      {
        "msg": {
          "mmsi": 538010632,
          "rig_name": "NOBLE INVINCIBLE",
          "latitude": 56.27456,
          "longitude": 3.399672,
          "msgtime": "2026-02-26T17:05:54.3666932+00:00",
          "source": "barentswatch"
        }
      }
    ],
    "msg_12h": null,
    "msg_1d": null,
    "msg_2d": null
  },
  "258615000": {
    "msg_recent": {
      "mmsi": 258615000,
      "rig_name": "TRANSOCEAN ENABLER",
      "latitude": 72.523775,
      "longitude": 20.344392,
      "msgtime": "2026-02-26T17:05:54+00:00",
      "source": "barentswatch"
    },
    "running_msgs": [
      {
        "msg": {
          "mmsi": 258615000,
          "rig_name": "TRANSOCEAN ENABLER",
          "latitude": 72.523775,
          "longitude": 20.344392,
          "msgtime": "2026-02-26T17:05:54+00:00",
          "source": "barentswatch"
        }
      }
    ],
    "msg_12h": null,
    "msg_1d": null,
    "msg_2d": null
  },
  "308928000": {
    "msg_recent": {
      "mmsi": 308928000,
      "rig_name": "SCARABEO 8",
      "latitude": 65.861815,
      "longitude": 7.396787,
      "msgtime": "2026-02-26T17:05:55.3658435+00:00",
      "source": "barentswatch"
    },
    "running_msgs": [
      {
        "msg": {
          "mmsi": 308928000,
          "rig_name": "SCARABEO 8",
          "latitude": 65.861815,
          "longitude": 7.396787,
          "msgtime": "2026-02-26T17:05:55.3658435+00:00",
          "source": "barentswatch"
        }
      }
    ],
    "msg_12h": null,
    "msg_1d": null,
    "msg_2d": null
  },
  "258627000": {
    "msg_recent": {
      "mmsi": 258627000,
      "rig_name": "TRANSOCEAN ENCOURAGE",
      "latitude": 65.03166666666667,
      "longitude": 6.873333333333333,
      "msgtime": "2026-02-26T16:58:52+00:00",
      "source": "barentswatch"
    },
    "running_msgs": [
      {
        "msg": {
          "mmsi": 258627000,
          "rig_name": "TRANSOCEAN ENCOURAGE",
          "latitude": 65.03166666666667,
          "longitude": 6.873333333333333,
          "msgtime": "2026-02-26T16:58:52+00:00",
          "source": "barentswatch"
        }
      }
    ],
    "msg_12h": null,
    "msg_1d": null,
    "msg_2d": null
  },
  "566391000": {
    "msg_recent": {
      "mmsi": 566391000,
      "rig_name": "COSLINNOVATOR",
      "latitude": 61.156927,
      "longitude": 3.468678,
      "msgtime": "2026-02-26T17:05:48+00:00",
      "source": "barentswatch"
    },
    "running_msgs": [
      {
        "msg": {
          "mmsi": 566391000,
          "rig_name": "COSLINNOVATOR",
          "latitude": 61.156927,
          "longitude": 3.468678,
          "msgtime": "2026-02-26T17:05:48+00:00",
          "source": "barentswatch"
        }
      }
    ],
    "msg_12h": null,
    "msg_1d": null,
    "msg_2d": null
  },
  "636016111": {
    "msg_recent": {
      "mmsi": 636016111,
      "rig_name": "SHELF DRILLING BARSK",
      "latitude": 58.418053,
      "longitude": 1.715857,
      "msgtime": "2026-02-26T17:04:54.3342241+00:00",
      "source": "barentswatch"
    },
    "running_msgs": [
      {
        "msg": {
          "mmsi": 636016111,
          "rig_name": "SHELF DRILLING BARSK",
          "latitude": 58.418053,
          "longitude": 1.715857,
          "msgtime": "2026-02-26T17:04:54.3342241+00:00",
          "source": "barentswatch"
        }
      }
    ],
    "msg_12h": null,
    "msg_1d": null,
    "msg_2d": null
  },
  "565798000": {
    "msg_recent": {
      "mmsi": 565798000,
      "rig_name": "COSLPROMOTER",
      "latitude": 61.275327,
      "longitude": 2.118363,
      "msgtime": "2026-02-26T17:03:43.0768656+00:00",
      "source": "barentswatch"
    },
    "running_msgs": [
      {
        "msg": {
          "mmsi": 565798000,
          "rig_name": "COSLPROMOTER",
          "latitude": 61.275327,
          "longitude": 2.118363,
          "msgtime": "2026-02-26T17:03:43.0768656+00:00",
          "source": "barentswatch"
        }
      }
    ],
    "msg_12h": null,
    "msg_1d": null,
    "msg_2d": null
  },
  "310766000": {
    "msg_recent": {
      "mmsi": 310766000,
      "rig_name": "DEEPSEA ATLANTIC",
      "latitude": 61.5275,
      "longitude": 2.31674,
      "msgtime": "2026-02-26T17:04:18.5150908+00:00",
      "source": "barentswatch"
    },
    "running_msgs": [
      {
        "msg": {
          "mmsi": 310766000,
          "rig_name": "DEEPSEA ATLANTIC",
          "latitude": 61.5275,
          "longitude": 2.31674,
          "msgtime": "2026-02-26T17:04:18.5150908+00:00",
          "source": "barentswatch"
        }
      }
    ],
    "msg_12h": null,
    "msg_1d": null,
    "msg_2d": null
  },
  "310767000": {
    "msg_recent": {
      "mmsi": 310767000,
      "rig_name": "DEEPSEA STAVANGER",
      "latitude": 60.111,
      "longitude": 2.592222,
      "msgtime": "2026-02-26T17:03:36.8669533+00:00",
      "source": "barentswatch"
    },
    "running_msgs": [
      {
        "msg": {
          "mmsi": 310767000,
          "rig_name": "DEEPSEA STAVANGER",
          "latitude": 60.111,
          "longitude": 2.592222,
          "msgtime": "2026-02-26T17:03:36.8669533+00:00",
          "source": "barentswatch"
        }
      }
    ],
    "msg_12h": null,
    "msg_1d": null,
    "msg_2d": null
  },
  "257440000": {
    "msg_recent": {
      "mmsi": 257440000,
      "rig_name": "DEEPSEA BOLLSTA",
      "latitude": 58.880295,
      "longitude": 2.487615,
      "msgtime": "2026-02-26T17:05:55.3658031+00:00",
      "source": "barentswatch"
    },
    "running_msgs": [
      {
        "msg": {
          "mmsi": 257440000,
          "rig_name": "DEEPSEA BOLLSTA",
          "latitude": 58.880295,
          "longitude": 2.487615,
          "msgtime": "2026-02-26T17:05:55.3658031+00:00",
          "source": "barentswatch"
        }
      }
    ],
    "msg_12h": null,
    "msg_1d": null,
    "msg_2d": null
  },
  "311000483": {
    "msg_recent": {
      "mmsi": 311000483,
      "rig_name": "DEEPSEA YANTAI",
      "latitude": 59.705333,
      "longitude": 2.308567,
      "msgtime": "2026-02-26T17:05:42.9575905+00:00",
      "source": "barentswatch"
    },
    "running_msgs": [
      {
        "msg": {
          "mmsi": 311000483,
          "rig_name": "DEEPSEA YANTAI",
          "latitude": 59.705333,
          "longitude": 2.308567,
          "msgtime": "2026-02-26T17:05:42.9575905+00:00",
          "source": "barentswatch"
        }
      }
    ],
    "msg_12h": null,
    "msg_1d": null,
    "msg_2d": null
  },
  "259783000": {
    "msg_recent": {
      "mmsi": 259783000,
      "rig_name": "WEST ELARA",
      "latitude": 56.548273,
      "longitude": 3.213778,
      "msgtime": "2026-02-26T17:05:48.16283+00:00",
      "source": "barentswatch"
    },
    "running_msgs": [
      {
        "msg": {
          "mmsi": 259783000,
          "rig_name": "WEST ELARA",
          "latitude": 56.548273,
          "longitude": 3.213778,
          "msgtime": "2026-02-26T17:05:48.16283+00:00",
          "source": "barentswatch"
        }
      }
    ],
    "msg_12h": null,
    "msg_1d": null,
    "msg_2d": null
  }
}