{
  "257452000": {
    "msg_recent": {
      "mmsi": 257452000,
      "rig_name": "ASKELADDEN",
      "latitude": 61.078512,
      "longitude": 1.988188,
      "msgtime": "2026-02-22T13:48:53.6562068+00:00",
      "source": "barentswatch"
    },
    "running_msgs": [
      {
        "msg": {
          "mmsi": 257452000,
          "rig_name": "ASKELADDEN",
          "latitude": 61.078512,
          "longitude": 1.988188,
          "msgtime": "2026-02-22T13:48:53.6562068+00:00",
          "source": "barentswatch"
        }
      }
    ],
    "msg_12h": null,
    "msg_1d": null,
    "msg_2d": null
  },
  "310713000": {
    "msg_recent": {
      "mmsi": 310713000,
      "rig_name": "DEEPSEA ABERDEEN",
      "latitude": 60.838327,
      "longitude": 3.551253,
      "msgtime": "2026-02-22T13:48:47+00:00",
      "source": "barentswatch"
    },
    "running_msgs": [
      {
        "msg": {
          "mmsi": 310713000,
          "rig_name": "DEEPSEA ABERDEEN",
          "latitude": 60.838327,
          "longitude": 3.551253,
          "msgtime": "2026-02-22T13:48:47+00:00",
          "source": "barentswatch"
        }
      }
    ],
    "msg_12h": null,
    "msg_1d": null,
    "msg_2d": null
  },
  "257459000": {
    "msg_recent": {
      "mmsi": 257459000,
      "rig_name": "ASKEPOTT",
      "latitude": 60.505603,
      "longitude": 2.015138,
      "msgtime": "2026-02-22T13:48:11.3060741+00:00",
      "source": "barentswatch"
    },
    "running_msgs": [
      {
        "msg": {
          "mmsi": 257459000,
          "rig_name": "ASKEPOTT",
          "latitude": 60.505603,
          "longitude": 2.015138,
          "msgtime": "2026-02-22T13:48:11.3060741+00:00",
          "source": "barentswatch"
        }
      }
    ],
    "msg_12h": null,
    "msg_1d": null,
    "msg_2d": null
  },
  "565369000": {
    "msg_recent": {
      "mmsi": 565369000,
      "rig_name": "COSLPROSPECTOR",
      "latitude": 72.367012,
      "longitude": 20.122322,
      "msgtime": "2026-02-22T13:48:47.5529106+00:00",
      "source": "barentswatch"
    },
    "running_msgs": [
      {
        "msg": {
          "mmsi": 565369000,
          "rig_name": "COSLPROSPECTOR",
          "latitude": 72.367012,
          "longitude": 20.122322,
          "msgtime": "2026-02-22T13:48:47.5529106+00:00",
          "source": "barentswatch"
        }
      }
    ],
    "msg_12h": null,
    "msg_1d": null,
    "msg_2d": null
  },
  "257095000": {
    "msg_recent": {
      "mmsi": 257095000,
      "rig_name": "LINUS",
      "latitude": 56.423177,
      "longitude": 3.210483,
      "msgtime": "2026-02-22T13:48:00.8928461+00:00",
      "source": "barentswatch"
    },
    "running_msgs": [
      {
        "msg": {
          "mmsi": 257095000,
          "rig_name": "LINUS",
          "latitude": 56.423177,
          "longitude": 3.210483,
          "msgtime": "2026-02-22T13:48:00.8928461+00:00",
          "source": "barentswatch"
        }
      }
    ],
    "msg_12h": null,
    "msg_1d": null,
    "msg_2d": null
  },
  "538004905": {
    "msg_recent": {
      "mmsi": 538004905,
      "rig_name": "TRANSOCEAN SPITSBERGEN",
      "latitude": 64.865,
      "longitude": 7.635000000000001,
      "msgtime": "2026-02-21T20:23:57+00:00",
      "source": "barentswatch"
    },
    "running_msgs": [
      {
        "msg": {
          "mmsi": 538004905,
          "rig_name": "TRANSOCEAN SPITSBERGEN",
          "latitude": 64.865,
          "longitude": 7.635000000000001,
          "msgtime": "2026-02-21T20:23:57+00:00",
          "source": "barentswatch"
        }
      }
    ],
    "msg_12h": null,
    "msg_1d": null,
    "msg_2d": null
  },
  "563050900": {
    "msg_recent": {
      "mmsi": 563050900,
      "rig_name": "COSLPIONEER",
      "latitude": 59.1995,
      "longitude": 2.4075,
      "msgtime": "2026-02-22T13:48:44.5522097+00:00",
      "source": "barentswatch"
    },
    "running_msgs": [
      {
        "msg": {
          "mmsi": 563050900,
          "rig_name": "COSLPIONEER",
          "latitude": 59.1995,
          "longitude": 2.4075,
          "msgtime": "2026-02-22T13:48:44.5522097+00:00",
          "source": "barentswatch"
        }
      }
    ],
    "msg_12h": null,
    "msg_1d": null,
    "msg_2d": null
  },
  "538010630": {
    "msg_recent": {
      "mmsi": 538010630,
      "rig_name": "NOBLE INTEGRATOR",
      "latitude": 59.871457,
      "longitude": 2.567657,
      "msgtime": "2026-02-22T09:33:33.2374612+00:00",
      "source": "barentswatch"
    },
    "running_msgs": [
      {
        "msg": {
          "mmsi": 538010630,
          "rig_name": "NOBLE INTEGRATOR",
          "latitude": 59.871457,
          "longitude": 2.567657,
          "msgtime": "2026-02-22T09:33:33.2374612+00:00",
          "source": "barentswatch"
        }
      }
    ],
    "msg_12h": null,
    "msg_1d": null,
    "msg_2d": null
  },
  "538010632": {
    "msg_recent": {
      "mmsi": 538010632,
      "rig_name": "NOBLE INVINCIBLE",
      "latitude": 56.274603,
      "longitude": 3.39964,
      "msgtime": "2026-02-22T13:47:29.8407084+00:00",
      "source": "barentswatch"
    },
    "running_msgs": [
      {
        "msg": {
          "mmsi": 538010632,
          "rig_name": "NOBLE INVINCIBLE",
          "latitude": 56.274603,
          "longitude": 3.39964,
          "msgtime": "2026-02-22T13:47:29.8407084+00:00",
          "source": "barentswatch"
        }
      }
    ],
    "msg_12h": null,
    "msg_1d": null,
    "msg_2d": null
  },
  "258615000": {
    "msg_recent": {
      "mmsi": 258615000,
      "rig_name": "TRANSOCEAN ENABLER",
      "latitude": 72.523992,
      "longitude": 20.344117,
      "msgtime": "2026-02-22T13:48:48.7549357+00:00",
      "source": "barentswatch"
    },
    "running_msgs": [
      {
        "msg": {
          "mmsi": 258615000,
          "rig_name": "TRANSOCEAN ENABLER",
          "latitude": 72.523992,
          "longitude": 20.344117,
          "msgtime": "2026-02-22T13:48:48.7549357+00:00",
          "source": "barentswatch"
        }
      }
    ],
    "msg_12h": null,
    "msg_1d": null,
    "msg_2d": null
  },
  "308928000": {
    "msg_recent": {
      "mmsi": 308928000,
      "rig_name": "SCARABEO 8",
      "latitude": 65.861812,
      "longitude": 7.396737,
      "msgtime": "2026-02-22T13:48:46.5537668+00:00",
      "source": "barentswatch"
    },
    "running_msgs": [
      {
        "msg": {
          "mmsi": 308928000,
          "rig_name": "SCARABEO 8",
          "latitude": 65.861812,
          "longitude": 7.396737,
          "msgtime": "2026-02-22T13:48:46.5537668+00:00",
          "source": "barentswatch"
        }
      }
    ],
    "msg_12h": null,
    "msg_1d": null,
    "msg_2d": null
  },
  "258627000": {
    "msg_recent": {
      "mmsi": 258627000,
      "rig_name": "TRANSOCEAN ENCOURAGE",
      "latitude": 65.03166666666667,
      "longitude": 6.873333333333333,
      "msgtime": "2026-02-22T12:49:54+00:00",
      "source": "barentswatch"
    },
    "running_msgs": [
      {
        "msg": {
          "mmsi": 258627000,
          "rig_name": "TRANSOCEAN ENCOURAGE",
          "latitude": 65.03166666666667,
          "longitude": 6.873333333333333,
          "msgtime": "2026-02-22T12:49:54+00:00",
          "source": "barentswatch"
        }
      }
    ],
    "msg_12h": null,
    "msg_1d": null,
    "msg_2d": null
  },
  "566391000": {
    "msg_recent": {
      "mmsi": 566391000,
      "rig_name": "COSLINNOVATOR",
      "latitude": 61.156952,
      "longitude": 3.468633,
      "msgtime": "2026-02-22T13:48:47+00:00",
      "source": "barentswatch"
    },
    "running_msgs": [
      {
        "msg": {
          "mmsi": 566391000,
          "rig_name": "COSLINNOVATOR",
          "latitude": 61.156952,
          "longitude": 3.468633,
          "msgtime": "2026-02-22T13:48:47+00:00",
          "source": "barentswatch"
        }
      }
    ],
    "msg_12h": null,
    "msg_1d": null,
    "msg_2d": null
  },
  "636016111": {
    "msg_recent": {
      "mmsi": 636016111,
      "rig_name": "SHELF DRILLING BARSK",
      "latitude": 58.418053,
      "longitude": 1.715865,
      "msgtime": "2026-02-22T13:45:02.5023036+00:00",
      "source": "barentswatch"
    },
    "running_msgs": [
      {
        "msg": {
          "mmsi": 636016111,
          "rig_name": "SHELF DRILLING BARSK",
          "latitude": 58.418053,
          "longitude": 1.715865,
          "msgtime": "2026-02-22T13:45:02.5023036+00:00",
          "source": "barentswatch"
        }
      }
    ],
    "msg_12h": null,
    "msg_1d": null,
    "msg_2d": null
  },
  "565798000": {
    "msg_recent": {
      "mmsi": 565798000,
      "rig_name": "COSLPROMOTER",
      "latitude": 61.275308,
      "longitude": 2.118378,
      "msgtime": "2026-02-22T13:46:13.9732023+00:00",
      "source": "barentswatch"
    },
    "running_msgs": [
      {
        "msg": {
          "mmsi": 565798000,
          "rig_name": "COSLPROMOTER",
          "latitude": 61.275308,
          "longitude": 2.118378,
          "msgtime": "2026-02-22T13:46:13.9732023+00:00",
          "source": "barentswatch"
        }
      }
    ],
    "msg_12h": null,
    "msg_1d": null,
    "msg_2d": null
  },
  "310766000": {
    "msg_recent": {
      "mmsi": 310766000,
      "rig_name": "DEEPSEA ATLANTIC",
      "latitude": 61.527493,
      "longitude": 2.316778,
      "msgtime": "2026-02-22T13:47:04+00:00",
      "source": "barentswatch"
    },
    "running_msgs": [
      {
        "msg": {
          "mmsi": 310766000,
          "rig_name": "DEEPSEA ATLANTIC",
          "latitude": 61.527493,
          "longitude": 2.316778,
          "msgtime": "2026-02-22T13:47:04+00:00",
          "source": "barentswatch"
        }
      }
    ],
    "msg_12h": null,
    "msg_1d": null,
    "msg_2d": null
  },
  "310767000": {
    "msg_recent": {
      "mmsi": 310767000,
      "rig_name": "DEEPSEA STAVANGER",
      "latitude": 60.111013,
      "longitude": 2.59219,
      "msgtime": "2026-02-22T13:47:30+00:00",
      "source": "barentswatch"
    },
    "running_msgs": [
      {
        "msg": {
          "mmsi": 310767000,
          "rig_name": "DEEPSEA STAVANGER",
          "latitude": 60.111013,
          "longitude": 2.59219,
          "msgtime": "2026-02-22T13:47:30+00:00",
          "source": "barentswatch"
        }
      }
    ],
    "msg_12h": null,
    "msg_1d": null,
    "msg_2d": null
  },
  "257440000": {
    "msg_recent": {
      "mmsi": 257440000,
      "rig_name": "DEEPSEA BOLLSTA",
      "latitude": 60.447897,
      "longitude": 2.436208,
      "msgtime": "2026-02-22T13:48:47.5520342+00:00",
      "source": "barentswatch"
    },
    "running_msgs": [
      {
        "msg": {
          "mmsi": 257440000,
          "rig_name": "DEEPSEA BOLLSTA",
          "latitude": 60.447897,
          "longitude": 2.436208,
          "msgtime": "2026-02-22T13:48:47.5520342+00:00",
          "source": "barentswatch"
        }
      }
    ],
    "msg_12h": null,
    "msg_1d": null,
    "msg_2d": null
  },
  "311000483": {
    "msg_recent": {
      "mmsi": 311000483,
      "rig_name": "DEEPSEA YANTAI",
      "latitude": 59.705367,
      "longitude": 2.308613,
      "msgtime": "2026-02-22T13:46:13.9762242+00:00",
      "source": "barentswatch"
    },
    "running_msgs": [
      {
        "msg": {
          "mmsi": 311000483,
          "rig_name": "DEEPSEA YANTAI",
          "latitude": 59.705367,
          "longitude": 2.308613,
          "msgtime": "2026-02-22T13:46:13.9762242+00:00",
          "source": "barentswatch"
        }
      }
    ],
    "msg_12h": null,
    "msg_1d": null,
    "msg_2d": null
  },
  "259783000": {
    "msg_recent": {
      "mmsi": 259783000,
      "rig_name": "WEST ELARA",
      "latitude": 56.54831,
      "longitude": 3.213768,
      "msgtime": "2026-02-22T13:48:48.7523168+00:00",
      "source": "barentswatch"
    },
    "running_msgs": [
      {
        "msg": {
          "mmsi": 259783000,
          "rig_name": "WEST ELARA",
          "latitude": 56.54831,
          "longitude": 3.213768,
          "msgtime": "2026-02-22T13:48:48.7523168+00:00",
          "source": "barentswatch"
        }
      }
    ],
    "msg_12h": null,
    "msg_1d": null,
    "msg_2d": null
  },
  "310776000": {
    "msg_recent": {
      "mmsi": 310776000,
      "rig_name": "DEEPSEA NORDKAPP",
      "latitude": 58.672202,
      "longitude": 2.23458,
      "msgtime": "2026-02-22T13:48:53.7590494+00:00",
      "source": "barentswatch"
    },
    "running_msgs": [
      {
        "msg": {
          "mmsi": 310776000,
          "rig_name": "DEEPSEA NORDKAPP",
          "latitude": 58.672202,
          "longitude": 2.23458,
          "msgtime": "2026-02-22T13:48:53.7590494+00:00",
          "source": "barentswatch"
        }
      }
    ],
    "msg_12h": null,
    "msg_1d": null,
    "msg_2d": null
  },
  "310776000": {
    "msg_recent": {
      "mmsi": 310776000,
      "rig_name": "DEEPSEA NORDKAPP",
      "latitude": 58.672198,
      "longitude": 2.234592,
      "msgtime": "2026-02-22T14:30:04.173331+00:00",
      "source": "barentswatch"
    },
    "running_msgs": [
      {
        "msg": {
          "mmsi": 310776000,
          "rig_name": "DEEPSEA NORDKAPP",
          "latitude": 58.672198,
          "longitude": 2.234592,
          "msgtime": "2026-02-22T14:30:04.173331+00:00",
          "source": "barentswatch"
        }
      }
    ],
    "msg_12h": null,
    "msg_1d": null,
    "msg_2d": null
  },
  "257452000": {
    "msg_recent": {
      "mmsi": 257452000,
      "rig_name": "ASKELADDEN",
      "latitude": 61.078512,
      "longitude": 1.98819,
      "msgtime": "2026-02-22T14:30:05.3724666+00:00",
      "source": "barentswatch"
    },
    "running_msgs": [
      {
        "msg": {
          "mmsi": 257452000,
          "rig_name": "ASKELADDEN",
          "latitude": 61.078512,
          "longitude": 1.98819,
          "msgtime": "2026-02-22T14:30:05.3724666+00:00",
          "source": "barentswatch"
        }
      }
    ],
    "msg_12h": null,
    "msg_1d": null,
    "msg_2d": null
  },
  "310713000": {
    "msg_recent": {
      "mmsi": 310713000,
      "rig_name": "DEEPSEA ABERDEEN",
      "latitude": 60.838333,
      "longitude": 3.551245,
      "msgtime": "2026-02-22T14:30:07+00:00",
      "source": "barentswatch"
    },
    "running_msgs": [
      {
        "msg": {
          "mmsi": 310713000,
          "rig_name": "DEEPSEA ABERDEEN",
          "latitude": 60.838333,
          "longitude": 3.551245,
          "msgtime": "2026-02-22T14:30:07+00:00",
          "source": "barentswatch"
        }
      }
    ],
    "msg_12h": null,
    "msg_1d": null,
    "msg_2d": null
  },
  "257459000": {
    "msg_recent": {
      "mmsi": 257459000,
      "rig_name": "ASKEPOTT",
      "latitude": 60.505583,
      "longitude": 2.015122,
      "msgtime": "2026-02-22T14:30:09.3736348+00:00",
      "source": "barentswatch"
    },
    "running_msgs": [
      {
        "msg": {
          "mmsi": 257459000,
          "rig_name": "ASKEPOTT",
          "latitude": 60.505583,
          "longitude": 2.015122,
          "msgtime": "2026-02-22T14:30:09.3736348+00:00",
          "source": "barentswatch"
        }
      }
    ],
    "msg_12h": null,
    "msg_1d": null,
    "msg_2d": null
  },
  "565369000": {
    "msg_recent": {
      "mmsi": 565369000,
      "rig_name": "COSLPROSPECTOR",
      "latitude": 72.367005,
      "longitude": 20.122368,
      "msgtime": "2026-02-22T14:30:08.3723038+00:00",
      "source": "barentswatch"
    },
    "running_msgs": [
      {
        "msg": {
          "mmsi": 565369000,
          "rig_name": "COSLPROSPECTOR",
          "latitude": 72.367005,
          "longitude": 20.122368,
          "msgtime": "2026-02-22T14:30:08.3723038+00:00",
          "source": "barentswatch"
        }
      }
    ],
    "msg_12h": null,
    "msg_1d": null,
    "msg_2d": null
  },
  "257095000": {
    "msg_recent": {
      "mmsi": 257095000,
      "rig_name": "LINUS",
      "latitude": 56.423188,
      "longitude": 3.210545,
      "msgtime": "2026-02-22T14:30:03.172749+00:00",
      "source": "barentswatch"
    },
    "running_msgs": [
      {
        "msg": {
          "mmsi": 257095000,
          "rig_name": "LINUS",
          "latitude": 56.423188,
          "longitude": 3.210545,
          "msgtime": "2026-02-22T14:30:03.172749+00:00",
          "source": "barentswatch"
        }
      }
    ],
    "msg_12h": null,
    "msg_1d": null,
    "msg_2d": null
  },
  "563050900": {
    "msg_recent": {
      "mmsi": 563050900,
      "rig_name": "COSLPIONEER",
      "latitude": 59.1995,
      "longitude": 2.4075,
      "msgtime": "2026-02-22T14:30:05.3725703+00:00",
      "source": "barentswatch"
    },
    "running_msgs": [
      {
        "msg": {
          "mmsi": 563050900,
          "rig_name": "COSLPIONEER",
          "latitude": 59.1995,
          "longitude": 2.4075,
          "msgtime": "2026-02-22T14:30:05.3725703+00:00",
          "source": "barentswatch"
        }
      }
    ],
    "msg_12h": null,
    "msg_1d": null,
    "msg_2d": null
  },
  "538010632": {
    "msg_recent": {
      "mmsi": 538010632,
      "rig_name": "NOBLE INVINCIBLE",
      "latitude": 56.274577,
      "longitude": 3.399742,
      "msgtime": "2026-02-22T14:29:28.956713+00:00",
      "source": "barentswatch"
    },
    "running_msgs": [
      {
        "msg": {
          "mmsi": 538010632,
          "rig_name": "NOBLE INVINCIBLE",
          "latitude": 56.274577,
          "longitude": 3.399742,
          "msgtime": "2026-02-22T14:29:28.956713+00:00",
          "source": "barentswatch"
        }
      }
    ],
    "msg_12h": null,
    "msg_1d": null,
    "msg_2d": null
  },
  "258615000": {
    "msg_recent": {
      "mmsi": 258615000,
      "rig_name": "TRANSOCEAN ENABLER",
      "latitude": 72.523995,
      "longitude": 20.34411,
      "msgtime": "2026-02-22T14:30:09.3735049+00:00",
      "source": "barentswatch"
    },
    "running_msgs": [
      {
        "msg": {
          "mmsi": 258615000,
          "rig_name": "TRANSOCEAN ENABLER",
          "latitude": 72.523995,
          "longitude": 20.34411,
          "msgtime": "2026-02-22T14:30:09.3735049+00:00",
          "source": "barentswatch"
        }
      }
    ],
    "msg_12h": null,
    "msg_1d": null,
    "msg_2d": null
  },
  "308928000": {
    "msg_recent": {
      "mmsi": 308928000,
      "rig_name": "SCARABEO 8",
      "latitude": 65.861833,
      "longitude": 7.396798,
      "msgtime": "2026-02-22T14:30:07.3745952+00:00",
      "source": "barentswatch"
    },
    "running_msgs": [
      {
        "msg": {
          "mmsi": 308928000,
          "rig_name": "SCARABEO 8",
          "latitude": 65.861833,
          "longitude": 7.396798,
          "msgtime": "2026-02-22T14:30:07.3745952+00:00",
          "source": "barentswatch"
        }
      }
    ],
    "msg_12h": null,
    "msg_1d": null,
    "msg_2d": null
  },
  "258627000": {
    "msg_recent": {
      "mmsi": 258627000,
      "rig_name": "TRANSOCEAN ENCOURAGE",
      "latitude": 65.03166666666667,
      "longitude": 6.873333333333333,
      "msgtime": "2026-02-22T14:22:53+00:00",
      "source": "barentswatch"
    },
    "running_msgs": [
      {
        "msg": {
          "mmsi": 258627000,
          "rig_name": "TRANSOCEAN ENCOURAGE",
          "latitude": 65.03166666666667,
          "longitude": 6.873333333333333,
          "msgtime": "2026-02-22T14:22:53+00:00",
          "source": "barentswatch"
        }
      }
    ],
    "msg_12h": null,
    "msg_1d": null,
    "msg_2d": null
  },
  "566391000": {
    "msg_recent": {
      "mmsi": 566391000,
      "rig_name": "COSLINNOVATOR",
      "latitude": 61.156927,
      "longitude": 3.468657,
      "msgtime": "2026-02-22T14:30:08+00:00",
      "source": "barentswatch"
    },
    "running_msgs": [
      {
        "msg": {
          "mmsi": 566391000,
          "rig_name": "COSLINNOVATOR",
          "latitude": 61.156927,
          "longitude": 3.468657,
          "msgtime": "2026-02-22T14:30:08+00:00",
          "source": "barentswatch"
        }
      }
    ],
    "msg_12h": null,
    "msg_1d": null,
    "msg_2d": null
  },
  "636016111": {
    "msg_recent": {
      "mmsi": 636016111,
      "rig_name": "SHELF DRILLING BARSK",
      "latitude": 58.41806,
      "longitude": 1.71582,
      "msgtime": "2026-02-22T14:26:58.7978201+00:00",
      "source": "barentswatch"
    },
    "running_msgs": [
      {
        "msg": {
          "mmsi": 636016111,
          "rig_name": "SHELF DRILLING BARSK",
          "latitude": 58.41806,
          "longitude": 1.71582,
          "msgtime": "2026-02-22T14:26:58.7978201+00:00",
          "source": "barentswatch"
        }
      }
    ],
    "msg_12h": null,
    "msg_1d": null,
    "msg_2d": null
  },
  "565798000": {
    "msg_recent": {
      "mmsi": 565798000,
      "rig_name": "COSLPROMOTER",
      "latitude": 61.275328,
      "longitude": 2.1184,
      "msgtime": "2026-02-22T14:27:45.4348128+00:00",
      "source": "barentswatch"
    },
    "running_msgs": [
      {
        "msg": {
          "mmsi": 565798000,
          "rig_name": "COSLPROMOTER",
          "latitude": 61.275328,
          "longitude": 2.1184,
          "msgtime": "2026-02-22T14:27:45.4348128+00:00",
          "source": "barentswatch"
        }
      }
    ],
    "msg_12h": null,
    "msg_1d": null,
    "msg_2d": null
  },
  "310766000": {
    "msg_recent": {
      "mmsi": 310766000,
      "rig_name": "DEEPSEA ATLANTIC",
      "latitude": 61.527493,
      "longitude": 2.316775,
      "msgtime": "2026-02-22T14:29:19.7548925+00:00",
      "source": "barentswatch"
    },
    "running_msgs": [
      {
        "msg": {
          "mmsi": 310766000,
          "rig_name": "DEEPSEA ATLANTIC",
          "latitude": 61.527493,
          "longitude": 2.316775,
          "msgtime": "2026-02-22T14:29:19.7548925+00:00",
          "source": "barentswatch"
        }
      }
    ],
    "msg_12h": null,
    "msg_1d": null,
    "msg_2d": null
  },
  "310767000": {
    "msg_recent": {
      "mmsi": 310767000,
      "rig_name": "DEEPSEA STAVANGER",
      "latitude": 60.111027,
      "longitude": 2.592192,
      "msgtime": "2026-02-22T14:29:30+00:00",
      "source": "barentswatch"
    },
    "running_msgs": [
      {
        "msg": {
          "mmsi": 310767000,
          "rig_name": "DEEPSEA STAVANGER",
          "latitude": 60.111027,
          "longitude": 2.592192,
          "msgtime": "2026-02-22T14:29:30+00:00",
          "source": "barentswatch"
        }
      }
    ],
    "msg_12h": null,
    "msg_1d": null,
    "msg_2d": null
  },
  "257440000": {
    "msg_recent": {
      "mmsi": 257440000,
      "rig_name": "DEEPSEA BOLLSTA",
      "latitude": 60.410847,
      "longitude": 2.437955,
      "msgtime": "2026-02-22T14:30:07.3745715+00:00",
      "source": "barentswatch"
    },
    "running_msgs": [
      {
        "msg": {
          "mmsi": 257440000,
          "rig_name": "DEEPSEA BOLLSTA",
          "latitude": 60.410847,
          "longitude": 2.437955,
          "msgtime": "2026-02-22T14:30:07.3745715+00:00",
          "source": "barentswatch"
        }
      }
    ],
    "msg_12h": null,
    "msg_1d": null,
    "msg_2d": null
  },
  "311000483": {
    "msg_recent": {
      "mmsi": 311000483,
      "rig_name": "DEEPSEA YANTAI",
      "latitude": 59.705367,
      "longitude": 2.308598,
      "msgtime": "2026-02-22T14:28:15.2775384+00:00",
      "source": "barentswatch"
    },
    "running_msgs": [
      {
        "msg": {
          "mmsi": 311000483,
          "rig_name": "DEEPSEA YANTAI",
          "latitude": 59.705367,
          "longitude": 2.308598,
          "msgtime": "2026-02-22T14:28:15.2775384+00:00",
          "source": "barentswatch"
        }
      }
    ],
    "msg_12h": null,
    "msg_1d": null,
    "msg_2d": null
  },
  "259783000": {
    "msg_recent": {
      "mmsi": 259783000,
      "rig_name": "WEST ELARA",
      "latitude": 56.548303,
      "longitude": 3.21379,
      "msgtime": "2026-02-22T14:29:47.756952+00:00",
      "source": "barentswatch"
    },
    "running_msgs": [
      {
        "msg": {
          "mmsi": 259783000,
          "rig_name": "WEST ELARA",
          "latitude": 56.548303,
          "longitude": 3.21379,
          "msgtime": "2026-02-22T14:29:47.756952+00:00",
          "source": "barentswatch"
        }
      }
    ],
    "msg_12h": null,
    "msg_1d": null,
    "msg_2d": null
  }
}