{
  "generated_at": "2026-06-12T08:49:06.127295+00:00",
  "rigs": {
    "ASKELADDEN": {
      "rig_name": "ASKELADDEN",
      "rig_type": "JACK-UP",
      "mmsi": "257452000",
      "lat": 61.096783,
      "lon": 2.275007,
      "last_seen": "2026-06-12T04:17:29.4529483+00:00",
      "rig_moving": false,
      "movement_m": null,
      "assigned_wells": [
        {
          "wellbore_name": "34/10-G-4 DH",
          "distance_m": 5.2,
          "approach_ratio": null
        }
      ],
      "num_assigned_wells": 1,
      "likely_target_well": "34/10-G-4 DH"
    },
    "DEEPSEA ABERDEEN": {
      "rig_name": "DEEPSEA ABERDEEN",
      "rig_type": "SEMISUB",
      "mmsi": "310713000",
      "lat": 59.230793,
      "lon": 2.55423,
      "last_seen": "2026-06-12T04:17:29.4529596+00:00",
      "rig_moving": false,
      "movement_m": null,
      "assigned_wells": [
        {
          "wellbore_name": "25/8-M-3 AH",
          "distance_m": 5318.4,
          "approach_ratio": null
        },
        {
          "wellbore_name": "25/8-M-3 BH",
          "distance_m": 5318.4,
          "approach_ratio": null
        },
        {
          "wellbore_name": "25/11-J-5 H",
          "distance_m": 40.1,
          "approach_ratio": null
        },
        {
          "wellbore_name": "25/11-J-4 H",
          "distance_m": 35.0,
          "approach_ratio": null
        },
        {
          "wellbore_name": "25/11-J-4 AH",
          "distance_m": 35.0,
          "approach_ratio": null
        },
        {
          "wellbore_name": "25/8-L-4 H",
          "distance_m": 3724.0,
          "approach_ratio": null
        },
        {
          "wellbore_name": "25/8-L-4 AH",
          "distance_m": 3724.0,
          "approach_ratio": null
        },
        {
          "wellbore_name": "25/11-J-5 AY1H",
          "distance_m": 40.1,
          "approach_ratio": null
        },
        {
          "wellbore_name": "25/11-J-5 AY2H",
          "distance_m": 40.1,
          "approach_ratio": null
        }
      ],
      "num_assigned_wells": 9,
      "likely_target_well": "25/11-J-4 H"
    },
    "ASKEPOTT": {
      "rig_name": "ASKEPOTT",
      "rig_type": "JACK-UP",
      "mmsi": "257459000",
      "lat": 60.505,
      "lon": 2.04,
      "last_seen": "2026-06-11T23:20:29+00:00",
      "rig_moving": false,
      "movement_m": null,
      "assigned_wells": [
        {
          "wellbore_name": "30/9-K-13 BH",
          "distance_m": 48436.9,
          "approach_ratio": null
        },
        {
          "wellbore_name": "30/4-A-18",
          "distance_m": 1475.1,
          "approach_ratio": null
        }
      ],
      "num_assigned_wells": 2,
      "likely_target_well": "30/4-A-18"
    },
    "COSLPROSPECTOR": {
      "rig_name": "COSLPROSPECTOR",
      "rig_type": "SEMISUB",
      "mmsi": "565369000",
      "lat": 64.03137,
      "lon": 6.74705,
      "last_seen": "2026-06-12T04:17:26+00:00",
      "rig_moving": false,
      "movement_m": null,
      "assigned_wells": [
        {
          "wellbore_name": "6406/12-G-4 H",
          "distance_m": 161.6,
          "approach_ratio": null
        },
        {
          "wellbore_name": "7122/10-E-1 Y2H",
          "distance_m": 1029738.1,
          "approach_ratio": null
        },
        {
          "wellbore_name": "7122/7-C-4 AH",
          "distance_m": 1033100.1,
          "approach_ratio": null
        }
      ],
      "num_assigned_wells": 3,
      "likely_target_well": "6406/12-G-4 H"
    },
    "LINUS": {
      "rig_name": "LINUS",
      "rig_type": "JACK-UP",
      "mmsi": "257095000",
      "lat": 56.548317,
      "lon": 3.213822,
      "last_seen": "2026-06-12T04:16:56.6011692+00:00",
      "rig_moving": false,
      "movement_m": null,
      "assigned_wells": [
        {
          "wellbore_name": "1/9-AA-6 H",
          "distance_m": 23936.6,
          "approach_ratio": null
        },
        {
          "wellbore_name": "2/7-S-30 B",
          "distance_m": 19731.7,
          "approach_ratio": null
        }
      ],
      "num_assigned_wells": 2,
      "likely_target_well": "2/7-S-30 B"
    },
    "TRANSOCEAN SPITSBERGEN": {
      "rig_name": "TRANSOCEAN SPITSBERGEN",
      "rig_type": "SEMISUB",
      "mmsi": "538004905",
      "lat": 64.880578,
      "lon": 6.433928,
      "last_seen": "2026-06-10T19:35:19.4435682+00:00",
      "rig_moving": false,
      "movement_m": null,
      "assigned_wells": [
        {
          "wellbore_name": "6406/2-L-1 Y2H",
          "distance_m": 6819.9,
          "approach_ratio": null
        },
        {
          "wellbore_name": "6406/2-L-3 Y2H",
          "distance_m": 6808.4,
          "approach_ratio": null
        },
        {
          "wellbore_name": "6406/2-L-4 Y2H",
          "distance_m": 6808.8,
          "approach_ratio": null
        }
      ],
      "num_assigned_wells": 3,
      "likely_target_well": "6406/2-L-3 Y2H"
    },
    "COSLPIONEER": {
      "rig_name": "COSLPIONEER",
      "rig_type": "SEMISUB",
      "mmsi": "563050900",
      "lat": 59.246333,
      "lon": 2.462667,
      "last_seen": "2026-06-12T04:17:32.1248177+00:00",
      "rig_moving": false,
      "movement_m": null,
      "assigned_wells": [
        {
          "wellbore_name": "25/11-HT-3 Y2H",
          "distance_m": 28.9,
          "approach_ratio": null
        },
        {
          "wellbore_name": "25/8-N-1 Y2H",
          "distance_m": 3374.4,
          "approach_ratio": null
        },
        {
          "wellbore_name": "25/8-N-1 Y3H",
          "distance_m": 3374.4,
          "approach_ratio": null
        },
        {
          "wellbore_name": "25/11-HT-4 Y2H",
          "distance_m": 32.5,
          "approach_ratio": null
        }
      ],
      "num_assigned_wells": 4,
      "likely_target_well": "25/11-HT-3 Y2H"
    },
    "NOBLE INTEGRATOR": {
      "rig_name": "NOBLE INTEGRATOR",
      "rig_type": "JACK-UP",
      "mmsi": "538010630",
      "lat": 59.871482,
      "lon": 2.567648,
      "last_seen": "2026-06-10T03:55:12+00:00",
      "rig_moving": false,
      "movement_m": null,
      "assigned_wells": [
        {
          "wellbore_name": "25/2-D-11 AY1",
          "distance_m": 106.0,
          "approach_ratio": null
        },
        {
          "wellbore_name": "25/2-D-11 AY2",
          "distance_m": 106.0,
          "approach_ratio": null
        },
        {
          "wellbore_name": "25/2-D-11 AY3",
          "distance_m": 106.0,
          "approach_ratio": null
        },
        {
          "wellbore_name": "25/2-D-6 Y2",
          "distance_m": 108.2,
          "approach_ratio": null
        },
        {
          "wellbore_name": "25/2-D-6 Y3",
          "distance_m": 108.2,
          "approach_ratio": null
        },
        {
          "wellbore_name": "25/2-D-14 AY1",
          "distance_m": 105.7,
          "approach_ratio": null
        },
        {
          "wellbore_name": "25/2-D-14 AY2",
          "distance_m": 105.7,
          "approach_ratio": null
        },
        {
          "wellbore_name": "25/2-D-14 AY3",
          "distance_m": 105.7,
          "approach_ratio": null
        }
      ],
      "num_assigned_wells": 8,
      "likely_target_well": "25/2-D-14 AY1"
    },
    "NOBLE INVINCIBLE": {
      "rig_name": "NOBLE INVINCIBLE",
      "rig_type": "JACK-UP",
      "mmsi": "538010632",
      "lat": 56.274597,
      "lon": 3.399555,
      "last_seen": "2026-06-12T04:17:11.1515584+00:00",
      "rig_moving": false,
      "movement_m": null,
      "assigned_wells": [],
      "num_assigned_wells": 0,
      "likely_target_well": null
    },
    "TRANSOCEAN ENABLER": {
      "rig_name": "TRANSOCEAN ENABLER",
      "rig_type": "SEMISUB",
      "mmsi": "258615000",
      "lat": 72.540713,
      "lon": 20.356207,
      "last_seen": "2026-06-12T04:17:32.6604469+00:00",
      "rig_moving": false,
      "movement_m": null,
      "assigned_wells": [
        {
          "wellbore_name": "7220/5-EB-1 Y2H",
          "distance_m": 1896.2,
          "approach_ratio": null
        },
        {
          "wellbore_name": "7220/5-EC-4 Y1H",
          "distance_m": 32.3,
          "approach_ratio": null
        },
        {
          "wellbore_name": "7220/5-EC-4 Y2H",
          "distance_m": 32.3,
          "approach_ratio": null
        },
        {
          "wellbore_name": "7220/5-EC-2 H",
          "distance_m": 22.8,
          "approach_ratio": null
        },
        {
          "wellbore_name": "7220/5-EC-2 AH",
          "distance_m": 22.8,
          "approach_ratio": null
        },
        {
          "wellbore_name": "7220/7-CC-1 Y1H",
          "distance_m": 18355.9,
          "approach_ratio": null
        },
        {
          "wellbore_name": "7220/7-CC-1 Y2H",
          "distance_m": 18355.9,
          "approach_ratio": null
        },
        {
          "wellbore_name": "7220/7-CC-3 H",
          "distance_m": 18367.7,
          "approach_ratio": null
        }
      ],
      "num_assigned_wells": 8,
      "likely_target_well": "7220/5-EC-2 H"
    },
    "SCARABEO 8": {
      "rig_name": "SCARABEO 8",
      "rig_type": "SEMISUB",
      "mmsi": "308928000",
      "lat": 66.001113,
      "lon": 7.79892,
      "last_seen": "2026-06-12T04:17:28+00:00",
      "rig_moving": false,
      "movement_m": null,
      "assigned_wells": [
        {
          "wellbore_name": "16/1-U-12",
          "distance_m": 830971.2,
          "approach_ratio": null
        },
        {
          "wellbore_name": "15/6-U-6",
          "distance_m": 871930.8,
          "approach_ratio": null
        },
        {
          "wellbore_name": "15/6-17",
          "distance_m": 871939.9,
          "approach_ratio": null
        },
        {
          "wellbore_name": "35/10-U-1",
          "distance_m": 591165.4,
          "approach_ratio": null
        }
      ],
      "num_assigned_wells": 4,
      "likely_target_well": "35/10-U-1"
    },
    "TRANSOCEAN ENCOURAGE": {
      "rig_name": "TRANSOCEAN ENCOURAGE",
      "rig_type": "SEMISUB",
      "mmsi": "258627000",
      "lat": 65.361282,
      "lon": 7.333632,
      "last_seen": "2026-06-12T04:17:30+00:00",
      "rig_moving": false,
      "movement_m": null,
      "assigned_wells": [
        {
          "wellbore_name": "6507/8-D-4 CH",
          "distance_m": 43.8,
          "approach_ratio": null
        },
        {
          "wellbore_name": "6507/8-D-4 DH",
          "distance_m": 43.8,
          "approach_ratio": null
        },
        {
          "wellbore_name": "6506/12-K-2 AH",
          "distance_m": 38695.4,
          "approach_ratio": null
        }
      ],
      "num_assigned_wells": 3,
      "likely_target_well": "6507/8-D-4 CH"
    },
    "COSLINNOVATOR": {
      "rig_name": "COSLINNOVATOR",
      "rig_type": "SEMISUB",
      "mmsi": "566391000",
      "lat": 59.340888,
      "lon": 2.222795,
      "last_seen": "2026-06-12T04:15:52.5312551+00:00",
      "rig_moving": false,
      "movement_m": null,
      "assigned_wells": [
        {
          "wellbore_name": "34/8-20 A",
          "distance_m": 239438.1,
          "approach_ratio": null
        },
        {
          "wellbore_name": "30/2-U-2",
          "distance_m": 178794.8,
          "approach_ratio": null
        },
        {
          "wellbore_name": "25/7-13",
          "distance_m": 40.8,
          "approach_ratio": null
        },
        {
          "wellbore_name": "16/2-24",
          "distance_m": 50479.7,
          "approach_ratio": null
        },
        {
          "wellbore_name": "16/2-24 A",
          "distance_m": 50479.7,
          "approach_ratio": null
        },
        {
          "wellbore_name": "34/10-56 S",
          "distance_m": 186694.7,
          "approach_ratio": null
        }
      ],
      "num_assigned_wells": 6,
      "likely_target_well": "25/7-13"
    },
    "SHELF DRILLING BARSK": {
      "rig_name": "SHELF DRILLING BARSK",
      "rig_type": "JACK-UP",
      "mmsi": "636016111",
      "lat": 58.41808,
      "lon": 1.715823,
      "last_seen": "2026-06-12T04:17:15.0287492+00:00",
      "rig_moving": false,
      "movement_m": null,
      "assigned_wells": [
        {
          "wellbore_name": "15/3-A-3",
          "distance_m": 47447.9,
          "approach_ratio": null
        },
        {
          "wellbore_name": "15/3-A-6 A",
          "distance_m": 47444.6,
          "approach_ratio": null
        }
      ],
      "num_assigned_wells": 2,
      "likely_target_well": "15/3-A-6 A"
    },
    "COSLPROMOTER": {
      "rig_name": "COSLPROMOTER",
      "rig_type": "SEMISUB",
      "mmsi": "565798000",
      "lat": 58.496103,
      "lon": 1.721243,
      "last_seen": "2026-06-12T04:15:18.0680987+00:00",
      "rig_moving": false,
      "movement_m": null,
      "assigned_wells": [
        {
          "wellbore_name": "15/5-C-2 H",
          "distance_m": 17275.0,
          "approach_ratio": null
        },
        {
          "wellbore_name": "15/9-E-2 AH",
          "distance_m": 36.1,
          "approach_ratio": null
        },
        {
          "wellbore_name": "16/7-A-2 AH",
          "distance_m": 30067.7,
          "approach_ratio": null
        }
      ],
      "num_assigned_wells": 3,
      "likely_target_well": "15/9-E-2 AH"
    },
    "DEEPSEA ATLANTIC": {
      "rig_name": "DEEPSEA ATLANTIC",
      "rig_type": "SEMISUB",
      "mmsi": "310766000",
      "lat": 60.415667,
      "lon": 5.007952,
      "last_seen": "2026-06-12T04:17:09+00:00",
      "rig_moving": false,
      "movement_m": null,
      "assigned_wells": [
        {
          "wellbore_name": "6610/7-3",
          "distance_m": 718538.8,
          "approach_ratio": null
        },
        {
          "wellbore_name": "25/11-30 A",
          "distance_m": 205954.0,
          "approach_ratio": null
        }
      ],
      "num_assigned_wells": 2,
      "likely_target_well": "25/11-30 A"
    },
    "DEEPSEA STAVANGER": {
      "rig_name": "DEEPSEA STAVANGER",
      "rig_type": "SEMISUB",
      "mmsi": "310767000",
      "lat": 60.221413,
      "lon": 2.49634,
      "last_seen": "2026-06-12T04:17:30.0699866+00:00",
      "rig_moving": false,
      "movement_m": null,
      "assigned_wells": [
        {
          "wellbore_name": "30/11-C-3 Y2H",
          "distance_m": 6884.8,
          "approach_ratio": null
        },
        {
          "wellbore_name": "30/11-V-6 H",
          "distance_m": 13384.6,
          "approach_ratio": null
        },
        {
          "wellbore_name": "30/11-W-1 H",
          "distance_m": 13346.4,
          "approach_ratio": null
        },
        {
          "wellbore_name": "30/11-W-4 H",
          "distance_m": 13333.9,
          "approach_ratio": null
        },
        {
          "wellbore_name": "30/11-Z-1 H",
          "distance_m": 33.3,
          "approach_ratio": null
        },
        {
          "wellbore_name": "30/11-Z-6 H",
          "distance_m": 30.6,
          "approach_ratio": null
        },
        {
          "wellbore_name": "30/11-W-4 AH",
          "distance_m": 13333.9,
          "approach_ratio": null
        },
        {
          "wellbore_name": "30/11-W-4 BH",
          "distance_m": 13333.9,
          "approach_ratio": null
        }
      ],
      "num_assigned_wells": 8,
      "likely_target_well": "30/11-Z-6 H"
    },
    "DEEPSEA BOLLSTA": {
      "rig_name": "DEEPSEA BOLLSTA",
      "rig_type": "SEMISUB",
      "mmsi": "257440000",
      "lat": 58.831628,
      "lon": 2.633252,
      "last_seen": "2026-06-12T04:17:32.124794+00:00",
      "rig_moving": false,
      "movement_m": null,
      "assigned_wells": [
        {
          "wellbore_name": "16/3-P-3 H",
          "distance_m": 5190.7,
          "approach_ratio": null
        },
        {
          "wellbore_name": "16/3-Q-3 H",
          "distance_m": 10148.4,
          "approach_ratio": null
        }
      ],
      "num_assigned_wells": 2,
      "likely_target_well": "16/3-P-3 H"
    },
    "DEEPSEA YANTAI": {
      "rig_name": "DEEPSEA YANTAI",
      "rig_type": "SEMISUB",
      "mmsi": "311000483",
      "lat": 61.000812,
      "lon": 3.13007,
      "last_seen": "2026-06-12T04:17:33+00:00",
      "rig_moving": false,
      "movement_m": null,
      "assigned_wells": [
        {
          "wellbore_name": "6506/11-U-5",
          "distance_m": 496277.6,
          "approach_ratio": null
        },
        {
          "wellbore_name": "6506/11-U-6",
          "distance_m": 496317.1,
          "approach_ratio": null
        },
        {
          "wellbore_name": "35/10-16 S",
          "distance_m": 40.5,
          "approach_ratio": null
        }
      ],
      "num_assigned_wells": 3,
      "likely_target_well": "35/10-16 S"
    },
    "WEST ELARA": {
      "rig_name": "WEST ELARA",
      "rig_type": "JACK-UP",
      "mmsi": "259783000",
      "lat": 59.617915,
      "lon": 2.494658,
      "last_seen": "2026-06-12T04:16:13.2926964+00:00",
      "rig_moving": false,
      "movement_m": null,
      "assigned_wells": [
        {
          "wellbore_name": "2/7-S-35 A",
          "distance_m": 363650.3,
          "approach_ratio": null
        }
      ],
      "num_assigned_wells": 1,
      "likely_target_well": "2/7-S-35 A"
    },
    "DEEPSEA NORDKAPP": {
      "rig_name": "DEEPSEA NORDKAPP",
      "rig_type": "SEMISUB",
      "mmsi": "310776000",
      "lat": 58.969523,
      "lon": 2.281222,
      "last_seen": "2026-06-12T04:17:30.069842+00:00",
      "rig_moving": false,
      "movement_m": null,
      "assigned_wells": [
        {
          "wellbore_name": "16/1-EA-1 Y1H",
          "distance_m": 33.2,
          "approach_ratio": null
        },
        {
          "wellbore_name": "16/1-EA-1 Y2H",
          "distance_m": 33.2,
          "approach_ratio": null
        },
        {
          "wellbore_name": "16/1-EA-1 Y3H",
          "distance_m": 33.2,
          "approach_ratio": null
        }
      ],
      "num_assigned_wells": 3,
      "likely_target_well": "16/1-EA-1 Y1H"
    }
  }
}